{
  "demo" : false,
  "instruments" : [ {
    "id" : "17c32bc4-1bb4-11eb-9d42-ab105d1d2821",
    "libraryId" : "53b95f54-fb24-11eb-ad24-8f1c28086c69",
    "type" : "Bass",
    "state" : "Published",
    "name" : "Earth Small Bass",
    "config" : "isTonal=true\nisMultiphonic=true",
    "isDeleted" : false,
    "volume" : 1.0,
    "mode" : "Event",
    "updatedAt" : 1706132003136
  } ],
  "instrumentAudios" : [ {
    "id" : "1e6bf043-efda-4aae-ae78-68d8868a5cf5",
    "instrumentId" : "17c32bc4-1bb4-11eb-9d42-ab105d1d2821",
    "name" : "A2",
    "waveformKey" : "Earth-Small-Bass-A2-A2.wav",
    "transientSeconds" : 0.0,
    "lengthSeconds" : 0.663242,
    "loopBeats" : 1.0,
    "tempo" : 120.0,
    "intensity" : 0.5,
    "event" : "BASS",
    "volume" : 1.0,
    "tones" : "A2"
  }, {
    "id" : "ea0d0ec4-5e30-4eef-a739-f1d14074cd49",
    "instrumentId" : "17c32bc4-1bb4-11eb-9d42-ab105d1d2821",
    "name" : "C3",
    "waveformKey" : "Earth-Small-Bass-C3-C3.wav",
    "transientSeconds" : 0.0,
    "lengthSeconds" : 0.685124,
    "loopBeats" : 1.0,
    "tempo" : 120.0,
    "intensity" : 0.5,
    "event" : "BASS",
    "volume" : 1.0,
    "tones" : "C3"
  }, {
    "id" : "50c5e0c9-bddc-41c6-bb43-56899f39b4a1",
    "instrumentId" : "17c32bc4-1bb4-11eb-9d42-ab105d1d2821",
    "name" : "A#2",
    "waveformKey" : "Earth-Small-Bass-As2-As2.wav",
    "transientSeconds" : 0.0,
    "lengthSeconds" : 0.725736,
    "loopBeats" : 1.0,
    "tempo" : 120.0,
    "intensity" : 0.5,
    "event" : "BASS",
    "volume" : 1.0,
    "tones" : "A#2"
  }, {
    "id" : "868f123a-49ae-447e-9106-111d9336a0ce",
    "instrumentId" : "17c32bc4-1bb4-11eb-9d42-ab105d1d2821",
    "name" : "C#2",
    "waveformKey" : "Earth-Small-Bass-Cs2-Cs2.wav",
    "transientSeconds" : 0.0,
    "lengthSeconds" : 0.688253,
    "loopBeats" : 1.0,
    "tempo" : 120.0,
    "intensity" : 0.5,
    "event" : "BASS",
    "volume" : 1.0,
    "tones" : "C#2"
  }, {
    "id" : "3da06abf-7ce9-4e33-b111-05cfdb7f45e3",
    "instrumentId" : "17c32bc4-1bb4-11eb-9d42-ab105d1d2821",
    "name" : "E1",
    "waveformKey" : "Earth-Small-Bass-E1-E1.wav",
    "transientSeconds" : 0.0,
    "lengthSeconds" : 0.732312,
    "loopBeats" : 1.0,
    "tempo" : 120.0,
    "intensity" : 0.5,
    "event" : "BASS",
    "volume" : 1.0,
    "tones" : "E1"
  }, {
    "id" : "1136cd48-a55f-427d-8b28-47592909d76d",
    "instrumentId" : "17c32bc4-1bb4-11eb-9d42-ab105d1d2821",
    "name" : "G#1",
    "waveformKey" : "Earth-Small-Bass-Gs1-Gs1.wav",
    "transientSeconds" : 0.0,
    "lengthSeconds" : 0.729591,
    "loopBeats" : 1.0,
    "tempo" : 120.0,
    "intensity" : 0.5,
    "event" : "BASS",
    "volume" : 1.0,
    "tones" : "G#1"
  }, {
    "id" : "7e9f7386-0ef5-4889-8443-1d71984301de",
    "instrumentId" : "17c32bc4-1bb4-11eb-9d42-ab105d1d2821",
    "name" : "B2",
    "waveformKey" : "Earth-Small-Bass-B2-B2.wav",
    "transientSeconds" : 0.0,
    "lengthSeconds" : 0.746145,
    "loopBeats" : 1.0,
    "tempo" : 120.0,
    "intensity" : 0.5,
    "event" : "BASS",
    "volume" : 1.0,
    "tones" : "B2"
  }, {
    "id" : "c89ae6fc-0a78-4a58-b500-94b0b9f55809",
    "instrumentId" : "17c32bc4-1bb4-11eb-9d42-ab105d1d2821",
    "name" : "C1",
    "waveformKey" : "Earth-Small-Bass-C1-C1.wav",
    "transientSeconds" : 0.0,
    "lengthSeconds" : 0.732312,
    "loopBeats" : 1.0,
    "tempo" : 120.0,
    "intensity" : 0.5,
    "event" : "BASS",
    "volume" : 1.0,
    "tones" : "C1"
  }, {
    "id" : "e7255597-ceca-428e-ab83-72548e0c5326",
    "instrumentId" : "17c32bc4-1bb4-11eb-9d42-ab105d1d2821",
    "name" : "G#2",
    "waveformKey" : "Earth-Small-Bass-Gs2-Gs2.wav",
    "transientSeconds" : 0.0,
    "lengthSeconds" : 0.709614,
    "loopBeats" : 1.0,
    "tempo" : 120.0,
    "intensity" : 0.5,
    "event" : "BASS",
    "volume" : 1.0,
    "tones" : "G#2"
  }, {
    "id" : "6f497102-ff3d-486a-9c0b-21d4447e3a6d",
    "instrumentId" : "17c32bc4-1bb4-11eb-9d42-ab105d1d2821",
    "name" : "B1",
    "waveformKey" : "Earth-Small-Bass-B1-B1.wav",
    "transientSeconds" : 0.0,
    "lengthSeconds" : 0.722471,
    "loopBeats" : 1.0,
    "tempo" : 120.0,
    "intensity" : 0.5,
    "event" : "BASS",
    "volume" : 1.0,
    "tones" : "B1"
  }, {
    "id" : "e1b92f0e-b4aa-4146-8a99-ecd8ff50365a",
    "instrumentId" : "17c32bc4-1bb4-11eb-9d42-ab105d1d2821",
    "name" : "D1",
    "waveformKey" : "Earth-Small-Bass-D1-D1.wav",
    "transientSeconds" : 0.0,
    "lengthSeconds" : 0.732312,
    "loopBeats" : 1.0,
    "tempo" : 120.0,
    "intensity" : 0.5,
    "event" : "BASS",
    "volume" : 1.0,
    "tones" : "D1"
  }, {
    "id" : "aa20c80a-1633-40aa-87ff-2833a59d5330",
    "instrumentId" : "17c32bc4-1bb4-11eb-9d42-ab105d1d2821",
    "name" : "G3",
    "waveformKey" : "Earth-Small-Bass-G3-G3.wav",
    "transientSeconds" : 0.0,
    "lengthSeconds" : 0.552222,
    "loopBeats" : 1.0,
    "tempo" : 120.0,
    "intensity" : 0.5,
    "event" : "BASS",
    "volume" : 1.0,
    "tones" : "G3"
  }, {
    "id" : "c9e1504b-c40e-4a4a-9796-61a220a2c2ac",
    "instrumentId" : "17c32bc4-1bb4-11eb-9d42-ab105d1d2821",
    "name" : "E3",
    "waveformKey" : "Earth-Small-Bass-E3-E3.wav",
    "transientSeconds" : 0.0,
    "lengthSeconds" : 0.722834,
    "loopBeats" : 1.0,
    "tempo" : 120.0,
    "intensity" : 0.5,
    "event" : "BASS",
    "volume" : 1.0,
    "tones" : "E3"
  }, {
    "id" : "5be7f6e4-1d69-48a3-ad6c-4ec5515a662e",
    "instrumentId" : "17c32bc4-1bb4-11eb-9d42-ab105d1d2821",
    "name" : "F2",
    "waveformKey" : "Earth-Small-Bass-F2-F2.wav",
    "transientSeconds" : 0.0,
    "lengthSeconds" : 0.677596,
    "loopBeats" : 1.0,
    "tempo" : 120.0,
    "intensity" : 0.5,
    "event" : "BASS",
    "volume" : 1.0,
    "tones" : "F2"
  }, {
    "id" : "734ff171-22e0-4d9b-b790-6cf17b54ed25",
    "instrumentId" : "17c32bc4-1bb4-11eb-9d42-ab105d1d2821",
    "name" : "E2",
    "waveformKey" : "Earth-Small-Bass-E2-E2.wav",
    "transientSeconds" : 0.0,
    "lengthSeconds" : 0.712448,
    "loopBeats" : 1.0,
    "tempo" : 120.0,
    "intensity" : 0.5,
    "event" : "BASS",
    "volume" : 1.0,
    "tones" : "E2"
  }, {
    "id" : "6c02c1a7-429b-4646-b481-52ea66585c1c",
    "instrumentId" : "17c32bc4-1bb4-11eb-9d42-ab105d1d2821",
    "name" : "F3",
    "waveformKey" : "Earth-Small-Bass-F3-F3.wav",
    "transientSeconds" : 0.0,
    "lengthSeconds" : 0.696122,
    "loopBeats" : 1.0,
    "tempo" : 120.0,
    "intensity" : 0.5,
    "event" : "BASS",
    "volume" : 1.0,
    "tones" : "F3"
  }, {
    "id" : "558f6520-9597-4f18-a671-85dde0ac2fb7",
    "instrumentId" : "17c32bc4-1bb4-11eb-9d42-ab105d1d2821",
    "name" : "D2",
    "waveformKey" : "Earth-Small-Bass-D2-D2.wav",
    "transientSeconds" : 0.0,
    "lengthSeconds" : 0.733469,
    "loopBeats" : 1.0,
    "tempo" : 120.0,
    "intensity" : 0.5,
    "event" : "BASS",
    "volume" : 1.0,
    "tones" : "D2"
  }, {
    "id" : "4fcea6af-d3f5-41aa-8163-864ab169e4a6",
    "instrumentId" : "17c32bc4-1bb4-11eb-9d42-ab105d1d2821",
    "name" : "C#1",
    "waveformKey" : "Earth-Small-Bass-Cs1-Cs1.wav",
    "transientSeconds" : 0.0,
    "lengthSeconds" : 0.732312,
    "loopBeats" : 1.0,
    "tempo" : 120.0,
    "intensity" : 0.5,
    "event" : "BASS",
    "volume" : 1.0,
    "tones" : "C#1"
  }, {
    "id" : "5b9965a0-6e88-4b28-a43d-69c76a1e9327",
    "instrumentId" : "17c32bc4-1bb4-11eb-9d42-ab105d1d2821",
    "name" : "F#2",
    "waveformKey" : "Earth-Small-Bass-Fs2-Fs2.wav",
    "transientSeconds" : 0.0,
    "lengthSeconds" : 0.686734,
    "loopBeats" : 1.0,
    "tempo" : 120.0,
    "intensity" : 0.5,
    "event" : "BASS",
    "volume" : 1.0,
    "tones" : "F#2"
  }, {
    "id" : "e1c87955-0d42-4c24-96c7-d9f69247dad1",
    "instrumentId" : "17c32bc4-1bb4-11eb-9d42-ab105d1d2821",
    "name" : "D3",
    "waveformKey" : "Earth-Small-Bass-D3-D3.wav",
    "transientSeconds" : 0.0,
    "lengthSeconds" : 0.684081,
    "loopBeats" : 1.0,
    "tempo" : 120.0,
    "intensity" : 0.5,
    "event" : "BASS",
    "volume" : 1.0,
    "tones" : "D3"
  }, {
    "id" : "f5e84cc5-fe15-4418-98c1-3c70d050f362",
    "instrumentId" : "17c32bc4-1bb4-11eb-9d42-ab105d1d2821",
    "name" : "D#1",
    "waveformKey" : "Earth-Small-Bass-Ds1-Ds1.wav",
    "transientSeconds" : 0.0,
    "lengthSeconds" : 0.732312,
    "loopBeats" : 1.0,
    "tempo" : 120.0,
    "intensity" : 0.5,
    "event" : "BASS",
    "volume" : 1.0,
    "tones" : "D#1"
  }, {
    "id" : "828d9193-e371-4f6a-9e0b-d97ca422d0f8",
    "instrumentId" : "17c32bc4-1bb4-11eb-9d42-ab105d1d2821",
    "name" : "F#3",
    "waveformKey" : "Earth-Small-Bass-Fs3-Fs3.wav",
    "transientSeconds" : 0.0,
    "lengthSeconds" : 0.744194,
    "loopBeats" : 1.0,
    "tempo" : 120.0,
    "intensity" : 0.5,
    "event" : "BASS",
    "volume" : 1.0,
    "tones" : "F#3"
  }, {
    "id" : "aa92539b-08ab-4fc2-a18b-e713695e0d4e",
    "instrumentId" : "17c32bc4-1bb4-11eb-9d42-ab105d1d2821",
    "name" : "G1",
    "waveformKey" : "Earth-Small-Bass-G1-G1.wav",
    "transientSeconds" : 0.0,
    "lengthSeconds" : 0.688707,
    "loopBeats" : 1.0,
    "tempo" : 120.0,
    "intensity" : 0.5,
    "event" : "BASS",
    "volume" : 1.0,
    "tones" : "G1"
  }, {
    "id" : "afc3fe72-7a64-42f5-ad5f-26218ded93da",
    "instrumentId" : "17c32bc4-1bb4-11eb-9d42-ab105d1d2821",
    "name" : "G2",
    "waveformKey" : "Earth-Small-Bass-G2-G2.wav",
    "transientSeconds" : 0.0,
    "lengthSeconds" : 0.758911,
    "loopBeats" : 1.0,
    "tempo" : 120.0,
    "intensity" : 0.5,
    "event" : "BASS",
    "volume" : 1.0,
    "tones" : "G2"
  }, {
    "id" : "67a60443-a0a9-4b1e-a99c-69f7e5e485b7",
    "instrumentId" : "17c32bc4-1bb4-11eb-9d42-ab105d1d2821",
    "name" : "C2",
    "waveformKey" : "Earth-Small-Bass-C2-C2.wav",
    "transientSeconds" : 0.0,
    "lengthSeconds" : 0.702494,
    "loopBeats" : 1.0,
    "tempo" : 120.0,
    "intensity" : 0.5,
    "event" : "BASS",
    "volume" : 1.0,
    "tones" : "C2"
  }, {
    "id" : "548b6a58-84c5-4003-adb1-980ceee639e2",
    "instrumentId" : "17c32bc4-1bb4-11eb-9d42-ab105d1d2821",
    "name" : "A#1",
    "waveformKey" : "Earth-Small-Bass-As1-As1.wav",
    "transientSeconds" : 0.0,
    "lengthSeconds" : 0.664852,
    "loopBeats" : 1.0,
    "tempo" : 120.0,
    "intensity" : 0.5,
    "event" : "BASS",
    "volume" : 1.0,
    "tones" : "A#1"
  }, {
    "id" : "478f1534-265a-47d5-a7e6-a0c176ac09cf",
    "instrumentId" : "17c32bc4-1bb4-11eb-9d42-ab105d1d2821",
    "name" : "D#2",
    "waveformKey" : "Earth-Small-Bass-Ds2-Ds2.wav",
    "transientSeconds" : 0.0,
    "lengthSeconds" : 0.677823,
    "loopBeats" : 1.0,
    "tempo" : 120.0,
    "intensity" : 0.5,
    "event" : "BASS",
    "volume" : 1.0,
    "tones" : "D#2"
  }, {
    "id" : "b3743981-15eb-4dfe-858c-49b60f897862",
    "instrumentId" : "17c32bc4-1bb4-11eb-9d42-ab105d1d2821",
    "name" : "F#1",
    "waveformKey" : "Earth-Small-Bass-Fs1-Fs1.wav",
    "transientSeconds" : 0.0,
    "lengthSeconds" : 0.713673,
    "loopBeats" : 1.0,
    "tempo" : 120.0,
    "intensity" : 0.5,
    "event" : "BASS",
    "volume" : 1.0,
    "tones" : "F#1"
  }, {
    "id" : "8a840c80-a18f-4a9a-954d-310e9b8d30ed",
    "instrumentId" : "17c32bc4-1bb4-11eb-9d42-ab105d1d2821",
    "name" : "C#3",
    "waveformKey" : "Earth-Small-Bass-Cs3-Cs3.wav",
    "transientSeconds" : 0.0,
    "lengthSeconds" : 0.702517,
    "loopBeats" : 1.0,
    "tempo" : 120.0,
    "intensity" : 0.5,
    "event" : "BASS",
    "volume" : 1.0,
    "tones" : "C#3"
  }, {
    "id" : "16ef9c39-6a2c-4836-8a29-af2c0100327e",
    "instrumentId" : "17c32bc4-1bb4-11eb-9d42-ab105d1d2821",
    "name" : "F1",
    "waveformKey" : "Earth-Small-Bass-F1-F1.wav",
    "transientSeconds" : 0.0,
    "lengthSeconds" : 0.690816,
    "loopBeats" : 1.0,
    "tempo" : 120.0,
    "intensity" : 0.5,
    "event" : "BASS",
    "volume" : 1.0,
    "tones" : "F1"
  }, {
    "id" : "454c33aa-9342-4de7-af28-782c37d57d29",
    "instrumentId" : "17c32bc4-1bb4-11eb-9d42-ab105d1d2821",
    "name" : "A1",
    "waveformKey" : "Earth-Small-Bass-A1-A1.wav",
    "transientSeconds" : 0.0,
    "lengthSeconds" : 0.722312,
    "loopBeats" : 1.0,
    "tempo" : 120.0,
    "intensity" : 0.5,
    "event" : "BASS",
    "volume" : 1.0,
    "tones" : "A1"
  }, {
    "id" : "db41f373-1743-4f9c-b061-f2cf16308ecc",
    "instrumentId" : "17c32bc4-1bb4-11eb-9d42-ab105d1d2821",
    "name" : "D#3",
    "waveformKey" : "Earth-Small-Bass-Ds3-Ds3.wav",
    "transientSeconds" : 0.0,
    "lengthSeconds" : 0.696802,
    "loopBeats" : 1.0,
    "tempo" : 120.0,
    "intensity" : 0.5,
    "event" : "BASS",
    "volume" : 1.0,
    "tones" : "D#3"
  } ],
  "instrumentMemes" : [ {
    "id" : "5b45d04f-504f-46b3-8792-0e3461eda67e",
    "instrumentId" : "17c32bc4-1bb4-11eb-9d42-ab105d1d2821",
    "name" : "EARTH"
  }, {
    "id" : "9e924058-1bb5-11eb-92b0-fff3fd22723c",
    "instrumentId" : "17c32bc4-1bb4-11eb-9d42-ab105d1d2821",
    "name" : "SMALL"
  } ]
}