{
  "demo" : false,
  "instrumentAudios" : [ {
    "id" : "606a7f62-9b39-4ab8-8366-c106bdb3305b",
    "instrumentId" : "f0c9f024-4f4c-11ed-b752-8bfe000d6dd5",
    "name" : "Eb sus4",
    "waveformKey" : "Tru-Arpy-Eb-sus4-Eb-sus4.wav",
    "transientSeconds" : 0.0,
    "lengthSeconds" : 8.227,
    "loopBeats" : 8.0,
    "tempo" : 120.0,
    "intensity" : 0.5,
    "event" : "PAD",
    "volume" : 1.0,
    "tones" : "Eb sus4"
  }, {
    "id" : "db6b3b41-4bb4-48b0-a3b9-028a4618b907",
    "instrumentId" : "f0c9f024-4f4c-11ed-b752-8bfe000d6dd5",
    "name" : "B dim7",
    "waveformKey" : "Tru-Arpy-B-dim7-B-dim7.wav",
    "transientSeconds" : 0.0,
    "lengthSeconds" : 8.227,
    "loopBeats" : 8.0,
    "tempo" : 120.0,
    "intensity" : 0.5,
    "event" : "PAD",
    "volume" : 1.0,
    "tones" : "B dim7"
  }, {
    "id" : "5b0967a1-e9f6-455f-8fe6-6d1fc7230ed9",
    "instrumentId" : "f0c9f024-4f4c-11ed-b752-8bfe000d6dd5",
    "name" : "F -7add9",
    "waveformKey" : "Tru-Arpy-F--7add9-F--7add9.wav",
    "transientSeconds" : 0.0,
    "lengthSeconds" : 8.227,
    "loopBeats" : 8.0,
    "tempo" : 120.0,
    "intensity" : 0.5,
    "event" : "PAD",
    "volume" : 1.0,
    "tones" : "F -7add9"
  }, {
    "id" : "a6ff94c5-6887-4999-b20e-398bc7e39d41",
    "instrumentId" : "f0c9f024-4f4c-11ed-b752-8bfe000d6dd5",
    "name" : "Gb sus2",
    "waveformKey" : "Tru-Arpy-Gb-sus2-Gb-sus2.wav",
    "transientSeconds" : 0.0,
    "lengthSeconds" : 8.227,
    "loopBeats" : 8.0,
    "tempo" : 120.0,
    "intensity" : 0.5,
    "event" : "PAD",
    "volume" : 1.0,
    "tones" : "Gb sus2"
  }, {
    "id" : "ae2d3ac6-2ba3-4780-90de-2b2c4478b441",
    "instrumentId" : "f0c9f024-4f4c-11ed-b752-8bfe000d6dd5",
    "name" : "D -7add9",
    "waveformKey" : "Tru-Arpy-D--7add9-D--7add9.wav",
    "transientSeconds" : 0.0,
    "lengthSeconds" : 8.227,
    "loopBeats" : 8.0,
    "tempo" : 120.0,
    "intensity" : 0.5,
    "event" : "PAD",
    "volume" : 1.0,
    "tones" : "D -7add9"
  }, {
    "id" : "2c0b516b-d5eb-4c4d-b958-96d007265f6b",
    "instrumentId" : "f0c9f024-4f4c-11ed-b752-8bfe000d6dd5",
    "name" : "F dim",
    "waveformKey" : "Tru-Arpy-F-dim-F-dim.wav",
    "transientSeconds" : 0.0,
    "lengthSeconds" : 8.227,
    "loopBeats" : 8.0,
    "tempo" : 120.0,
    "intensity" : 0.5,
    "event" : "PAD",
    "volume" : 1.0,
    "tones" : "F dim"
  }, {
    "id" : "e35208b0-2987-44b6-9233-80b843aa30f6",
    "instrumentId" : "f0c9f024-4f4c-11ed-b752-8bfe000d6dd5",
    "name" : "E dim",
    "waveformKey" : "Tru-Arpy-E-dim-E-dim.wav",
    "transientSeconds" : 0.0,
    "lengthSeconds" : 8.227,
    "loopBeats" : 8.0,
    "tempo" : 120.0,
    "intensity" : 0.5,
    "event" : "PAD",
    "volume" : 1.0,
    "tones" : "E dim"
  }, {
    "id" : "84c65a9d-c71e-4b71-b4d2-29bd7cd2ea8c",
    "instrumentId" : "f0c9f024-4f4c-11ed-b752-8bfe000d6dd5",
    "name" : "A -7add9",
    "waveformKey" : "Tru-Arpy-A--7add9-A--7add9.wav",
    "transientSeconds" : 0.0,
    "lengthSeconds" : 8.227,
    "loopBeats" : 8.0,
    "tempo" : 120.0,
    "intensity" : 0.5,
    "event" : "PAD",
    "volume" : 1.0,
    "tones" : "A -7add9"
  }, {
    "id" : "0ce932a6-9aed-4dc4-baea-ab2fd9cf1465",
    "instrumentId" : "f0c9f024-4f4c-11ed-b752-8bfe000d6dd5",
    "name" : "Gb maj7",
    "waveformKey" : "Tru-Arpy-Gb-maj7-Gb-maj7.wav",
    "transientSeconds" : 0.0,
    "lengthSeconds" : 8.227,
    "loopBeats" : 8.0,
    "tempo" : 120.0,
    "intensity" : 0.5,
    "event" : "PAD",
    "volume" : 1.0,
    "tones" : "Gb maj7"
  }, {
    "id" : "22a6a348-dd81-4a06-addb-bebdfa41f343",
    "instrumentId" : "f0c9f024-4f4c-11ed-b752-8bfe000d6dd5",
    "name" : "E 7",
    "waveformKey" : "Tru-Arpy-E-7-E-7.wav",
    "transientSeconds" : 0.0,
    "lengthSeconds" : 8.227,
    "loopBeats" : 8.0,
    "tempo" : 120.0,
    "intensity" : 0.5,
    "event" : "PAD",
    "volume" : 1.0,
    "tones" : "E 7"
  }, {
    "id" : "60db2bf6-9dc6-4436-b107-d2be6bc8cfa2",
    "instrumentId" : "f0c9f024-4f4c-11ed-b752-8bfe000d6dd5",
    "name" : "Bb maj7",
    "waveformKey" : "Tru-Arpy-Bb-maj7-Bb-maj7.wav",
    "transientSeconds" : 0.0,
    "lengthSeconds" : 8.227,
    "loopBeats" : 8.0,
    "tempo" : 120.0,
    "intensity" : 0.5,
    "event" : "PAD",
    "volume" : 1.0,
    "tones" : "Bb maj7"
  }, {
    "id" : "2e1a6a5d-b686-4ac9-923a-0f92b737b898",
    "instrumentId" : "f0c9f024-4f4c-11ed-b752-8bfe000d6dd5",
    "name" : "Bb 7b9",
    "waveformKey" : "Tru-Arpy-Bb-7b9-Bb-7b9.wav",
    "transientSeconds" : 0.0,
    "lengthSeconds" : 8.227,
    "loopBeats" : 8.0,
    "tempo" : 120.0,
    "intensity" : 0.5,
    "event" : "PAD",
    "volume" : 1.0,
    "tones" : "Bb 7b9"
  }, {
    "id" : "e6fa6911-bd32-4543-ad80-1e3273ee83d2",
    "instrumentId" : "f0c9f024-4f4c-11ed-b752-8bfe000d6dd5",
    "name" : "Eb",
    "waveformKey" : "Tru-Arpy-Eb-Eb.wav",
    "transientSeconds" : 0.0,
    "lengthSeconds" : 8.227,
    "loopBeats" : 8.0,
    "tempo" : 120.0,
    "intensity" : 0.5,
    "event" : "PAD",
    "volume" : 1.0,
    "tones" : "Eb"
  }, {
    "id" : "cef96505-d89f-4159-840e-056cb07e9a30",
    "instrumentId" : "f0c9f024-4f4c-11ed-b752-8bfe000d6dd5",
    "name" : "Eb -7b5",
    "waveformKey" : "Tru-Arpy-Eb--7b5-Eb--7b5.wav",
    "transientSeconds" : 0.0,
    "lengthSeconds" : 8.227,
    "loopBeats" : 8.0,
    "tempo" : 120.0,
    "intensity" : 0.5,
    "event" : "PAD",
    "volume" : 1.0,
    "tones" : "Eb -7b5"
  }, {
    "id" : "677972ae-d340-4fda-a45f-5f5f8509f55c",
    "instrumentId" : "f0c9f024-4f4c-11ed-b752-8bfe000d6dd5",
    "name" : "Db sus4",
    "waveformKey" : "Tru-Arpy-Db-sus4-Db-sus4.wav",
    "transientSeconds" : 0.0,
    "lengthSeconds" : 8.227,
    "loopBeats" : 8.0,
    "tempo" : 120.0,
    "intensity" : 0.5,
    "event" : "PAD",
    "volume" : 1.0,
    "tones" : "Db sus4"
  }, {
    "id" : "9a0ee90b-9405-429f-856d-37d83bf3aac1",
    "instrumentId" : "f0c9f024-4f4c-11ed-b752-8bfe000d6dd5",
    "name" : "G 7",
    "waveformKey" : "Tru-Arpy-G-7-G-7.wav",
    "transientSeconds" : 0.0,
    "lengthSeconds" : 8.227,
    "loopBeats" : 8.0,
    "tempo" : 120.0,
    "intensity" : 0.5,
    "event" : "PAD",
    "volume" : 1.0,
    "tones" : "G 7"
  }, {
    "id" : "b5b43218-531e-4d42-80d2-ab22f5f66aef",
    "instrumentId" : "f0c9f024-4f4c-11ed-b752-8bfe000d6dd5",
    "name" : "Db -7b5",
    "waveformKey" : "Tru-Arpy-Db--7b5-Db--7b5.wav",
    "transientSeconds" : 0.0,
    "lengthSeconds" : 8.227,
    "loopBeats" : 8.0,
    "tempo" : 120.0,
    "intensity" : 0.5,
    "event" : "PAD",
    "volume" : 1.0,
    "tones" : "Db -7b5"
  }, {
    "id" : "c5143f76-4ed0-4009-9468-6df2f202963a",
    "instrumentId" : "f0c9f024-4f4c-11ed-b752-8bfe000d6dd5",
    "name" : "Eb maj7",
    "waveformKey" : "Tru-Arpy-Eb-maj7-Eb-maj7.wav",
    "transientSeconds" : 0.0,
    "lengthSeconds" : 8.227,
    "loopBeats" : 8.0,
    "tempo" : 120.0,
    "intensity" : 0.5,
    "event" : "PAD",
    "volume" : 1.0,
    "tones" : "Eb maj7"
  }, {
    "id" : "8b7c9164-0e7b-4cad-85a4-993a757e5135",
    "instrumentId" : "f0c9f024-4f4c-11ed-b752-8bfe000d6dd5",
    "name" : "C min",
    "waveformKey" : "Tru-Arpy-C-min-C--.wav",
    "transientSeconds" : 0.0,
    "lengthSeconds" : 8.227,
    "loopBeats" : 8.0,
    "tempo" : 120.0,
    "intensity" : 0.5,
    "event" : "PAD",
    "volume" : 1.0,
    "tones" : "C -"
  }, {
    "id" : "58aa359e-3d9e-4379-9f97-6a14ff8f62c3",
    "instrumentId" : "f0c9f024-4f4c-11ed-b752-8bfe000d6dd5",
    "name" : "C sus2",
    "waveformKey" : "Tru-Arpy-C-sus2-C-sus2.wav",
    "transientSeconds" : 0.0,
    "lengthSeconds" : 8.227,
    "loopBeats" : 8.0,
    "tempo" : 120.0,
    "intensity" : 0.5,
    "event" : "PAD",
    "volume" : 1.0,
    "tones" : "C sus2"
  }, {
    "id" : "5b69fd25-86f7-4a45-9e7d-aef84c424724",
    "instrumentId" : "f0c9f024-4f4c-11ed-b752-8bfe000d6dd5",
    "name" : "Ab dim",
    "waveformKey" : "Tru-Arpy-Ab-dim-Ab-dim.wav",
    "transientSeconds" : 0.0,
    "lengthSeconds" : 8.227,
    "loopBeats" : 8.0,
    "tempo" : 120.0,
    "intensity" : 0.5,
    "event" : "PAD",
    "volume" : 1.0,
    "tones" : "Ab dim"
  }, {
    "id" : "4001b09b-8041-4b23-919e-586c07e49ece",
    "instrumentId" : "f0c9f024-4f4c-11ed-b752-8bfe000d6dd5",
    "name" : "A 7b9",
    "waveformKey" : "Tru-Arpy-A-7b9-A-7b9.wav",
    "transientSeconds" : 0.0,
    "lengthSeconds" : 8.227,
    "loopBeats" : 8.0,
    "tempo" : 120.0,
    "intensity" : 0.5,
    "event" : "PAD",
    "volume" : 1.0,
    "tones" : "A 7b9"
  }, {
    "id" : "7ba956ab-21c3-4f8c-9d6c-6f2eae266108",
    "instrumentId" : "f0c9f024-4f4c-11ed-b752-8bfe000d6dd5",
    "name" : "A dim",
    "waveformKey" : "Tru-Arpy-A-dim-A-dim.wav",
    "transientSeconds" : 0.0,
    "lengthSeconds" : 8.227,
    "loopBeats" : 8.0,
    "tempo" : 120.0,
    "intensity" : 0.5,
    "event" : "PAD",
    "volume" : 1.0,
    "tones" : "A dim"
  }, {
    "id" : "10866b1f-29e1-4e21-9e84-e6c30d17af2b",
    "instrumentId" : "f0c9f024-4f4c-11ed-b752-8bfe000d6dd5",
    "name" : "B maj7",
    "waveformKey" : "Tru-Arpy-B-maj7-B-maj7.wav",
    "transientSeconds" : 0.0,
    "lengthSeconds" : 8.227,
    "loopBeats" : 8.0,
    "tempo" : 120.0,
    "intensity" : 0.5,
    "event" : "PAD",
    "volume" : 1.0,
    "tones" : "B maj7"
  }, {
    "id" : "ecb8c6e0-693c-4fa9-9d9d-67d5951729b7",
    "instrumentId" : "f0c9f024-4f4c-11ed-b752-8bfe000d6dd5",
    "name" : "C 7sus4",
    "waveformKey" : "Tru-Arpy-C-7sus4-C-7sus4.wav",
    "transientSeconds" : 0.0,
    "lengthSeconds" : 8.227,
    "loopBeats" : 8.0,
    "tempo" : 120.0,
    "intensity" : 0.5,
    "event" : "PAD",
    "volume" : 1.0,
    "tones" : "C 7sus4"
  }, {
    "id" : "ea8033b5-ad82-4957-b849-0f9f5c1ee50d",
    "instrumentId" : "f0c9f024-4f4c-11ed-b752-8bfe000d6dd5",
    "name" : "Db",
    "waveformKey" : "Tru-Arpy-Db-Db.wav",
    "transientSeconds" : 0.0,
    "lengthSeconds" : 8.227,
    "loopBeats" : 8.0,
    "tempo" : 120.0,
    "intensity" : 0.5,
    "event" : "PAD",
    "volume" : 1.0,
    "tones" : "Db"
  }, {
    "id" : "df501978-9621-44f0-b1a4-1a141d002f6f",
    "instrumentId" : "f0c9f024-4f4c-11ed-b752-8bfe000d6dd5",
    "name" : "F 7b9",
    "waveformKey" : "Tru-Arpy-F-7b9-F-7b9.wav",
    "transientSeconds" : 0.0,
    "lengthSeconds" : 8.227,
    "loopBeats" : 8.0,
    "tempo" : 120.0,
    "intensity" : 0.5,
    "event" : "PAD",
    "volume" : 1.0,
    "tones" : "F 7b9"
  }, {
    "id" : "28569bb7-e75b-4fbf-b573-8fa3b935facb",
    "instrumentId" : "f0c9f024-4f4c-11ed-b752-8bfe000d6dd5",
    "name" : "G -7",
    "waveformKey" : "Tru-Arpy-G--7-G--7.wav",
    "transientSeconds" : 0.0,
    "lengthSeconds" : 8.227,
    "loopBeats" : 8.0,
    "tempo" : 120.0,
    "intensity" : 0.5,
    "event" : "PAD",
    "volume" : 1.0,
    "tones" : "G -7"
  }, {
    "id" : "e24a98ae-2e2b-41be-b22a-36a0b4f8182f",
    "instrumentId" : "f0c9f024-4f4c-11ed-b752-8bfe000d6dd5",
    "name" : "Bb 7",
    "waveformKey" : "Tru-Arpy-Bb-7-Bb-7.wav",
    "transientSeconds" : 0.0,
    "lengthSeconds" : 8.227,
    "loopBeats" : 8.0,
    "tempo" : 120.0,
    "intensity" : 0.5,
    "event" : "PAD",
    "volume" : 1.0,
    "tones" : "Bb 7"
  }, {
    "id" : "0854f746-a455-4d29-a9a0-b0472cbf4407",
    "instrumentId" : "f0c9f024-4f4c-11ed-b752-8bfe000d6dd5",
    "name" : "D min",
    "waveformKey" : "Tru-Arpy-D-min-D--.wav",
    "transientSeconds" : 0.0,
    "lengthSeconds" : 8.227,
    "loopBeats" : 8.0,
    "tempo" : 120.0,
    "intensity" : 0.5,
    "event" : "PAD",
    "volume" : 1.0,
    "tones" : "D -"
  }, {
    "id" : "3480112a-b0ff-47ac-aa4d-ecd040a1b1f6",
    "instrumentId" : "f0c9f024-4f4c-11ed-b752-8bfe000d6dd5",
    "name" : "E 7sus4",
    "waveformKey" : "Tru-Arpy-E-7sus4-E-7sus4.wav",
    "transientSeconds" : 0.0,
    "lengthSeconds" : 8.227,
    "loopBeats" : 8.0,
    "tempo" : 120.0,
    "intensity" : 0.5,
    "event" : "PAD",
    "volume" : 1.0,
    "tones" : "E 7sus4"
  }, {
    "id" : "4196b2df-70e8-48a5-beeb-97e9145c6069",
    "instrumentId" : "f0c9f024-4f4c-11ed-b752-8bfe000d6dd5",
    "name" : "E -7add9",
    "waveformKey" : "Tru-Arpy-E--7add9-E--7add9.wav",
    "transientSeconds" : 0.0,
    "lengthSeconds" : 8.227,
    "loopBeats" : 8.0,
    "tempo" : 120.0,
    "intensity" : 0.5,
    "event" : "PAD",
    "volume" : 1.0,
    "tones" : "E -7add9"
  }, {
    "id" : "cbbfaea9-c655-4496-bd91-4d6826809f99",
    "instrumentId" : "f0c9f024-4f4c-11ed-b752-8bfe000d6dd5",
    "name" : "G -7b5",
    "waveformKey" : "Tru-Arpy-G--7b5-G--7b5.wav",
    "transientSeconds" : 0.0,
    "lengthSeconds" : 8.227,
    "loopBeats" : 8.0,
    "tempo" : 120.0,
    "intensity" : 0.5,
    "event" : "PAD",
    "volume" : 1.0,
    "tones" : "G -7b5"
  }, {
    "id" : "12973183-7fa8-40fd-a3b9-d8f73fc67ffc",
    "instrumentId" : "f0c9f024-4f4c-11ed-b752-8bfe000d6dd5",
    "name" : "C 7b9",
    "waveformKey" : "Tru-Arpy-C-7b9-C-7b9.wav",
    "transientSeconds" : 0.0,
    "lengthSeconds" : 8.227,
    "loopBeats" : 8.0,
    "tempo" : 120.0,
    "intensity" : 0.5,
    "event" : "PAD",
    "volume" : 1.0,
    "tones" : "C 7b9"
  }, {
    "id" : "a735e73f-8c74-41f3-84b3-3a9f68b7162e",
    "instrumentId" : "f0c9f024-4f4c-11ed-b752-8bfe000d6dd5",
    "name" : "E maj7",
    "waveformKey" : "Tru-Arpy-E-maj7-E-maj7.wav",
    "transientSeconds" : 0.0,
    "lengthSeconds" : 8.227,
    "loopBeats" : 8.0,
    "tempo" : 120.0,
    "intensity" : 0.5,
    "event" : "PAD",
    "volume" : 1.0,
    "tones" : "E maj7"
  }, {
    "id" : "b144e281-27d2-4103-b56e-9763c8e9c2c8",
    "instrumentId" : "f0c9f024-4f4c-11ed-b752-8bfe000d6dd5",
    "name" : "Ab 7b9",
    "waveformKey" : "Tru-Arpy-Ab-7b9-Ab-7b9.wav",
    "transientSeconds" : 0.0,
    "lengthSeconds" : 8.227,
    "loopBeats" : 8.0,
    "tempo" : 120.0,
    "intensity" : 0.5,
    "event" : "PAD",
    "volume" : 1.0,
    "tones" : "Ab 7b9"
  }, {
    "id" : "4c67c6b7-131c-47f5-9af9-17623e7afbe2",
    "instrumentId" : "f0c9f024-4f4c-11ed-b752-8bfe000d6dd5",
    "name" : "Bb -7b5",
    "waveformKey" : "Tru-Arpy-Bb--7b5-Bb--7b5.wav",
    "transientSeconds" : 0.0,
    "lengthSeconds" : 8.227,
    "loopBeats" : 8.0,
    "tempo" : 120.0,
    "intensity" : 0.5,
    "event" : "PAD",
    "volume" : 1.0,
    "tones" : "Bb -7b5"
  }, {
    "id" : "a7e83aa4-833d-4144-a6c3-4f8baaab3fed",
    "instrumentId" : "f0c9f024-4f4c-11ed-b752-8bfe000d6dd5",
    "name" : "F 7",
    "waveformKey" : "Tru-Arpy-F-7-F-7.wav",
    "transientSeconds" : 0.0,
    "lengthSeconds" : 8.227,
    "loopBeats" : 8.0,
    "tempo" : 120.0,
    "intensity" : 0.5,
    "event" : "PAD",
    "volume" : 1.0,
    "tones" : "F 7"
  }, {
    "id" : "18a98123-b29f-468a-bced-11a77a5842b0",
    "instrumentId" : "f0c9f024-4f4c-11ed-b752-8bfe000d6dd5",
    "name" : "E -7",
    "waveformKey" : "Tru-Arpy-E--7-E--7.wav",
    "transientSeconds" : 0.0,
    "lengthSeconds" : 8.227,
    "loopBeats" : 8.0,
    "tempo" : 120.0,
    "intensity" : 0.5,
    "event" : "PAD",
    "volume" : 1.0,
    "tones" : "E -7"
  }, {
    "id" : "f71ef5d2-3fac-4344-8f62-6328316a3439",
    "instrumentId" : "f0c9f024-4f4c-11ed-b752-8bfe000d6dd5",
    "name" : "Eb aug",
    "waveformKey" : "Tru-Arpy-Eb-aug-Eb-aug.wav",
    "transientSeconds" : 0.0,
    "lengthSeconds" : 8.227,
    "loopBeats" : 8.0,
    "tempo" : 120.0,
    "intensity" : 0.5,
    "event" : "PAD",
    "volume" : 1.0,
    "tones" : "Eb aug"
  }, {
    "id" : "5ffa5953-c2ff-4c2c-8132-3edae92aa585",
    "instrumentId" : "f0c9f024-4f4c-11ed-b752-8bfe000d6dd5",
    "name" : "B",
    "waveformKey" : "Tru-Arpy-B-B.wav",
    "transientSeconds" : 0.0,
    "lengthSeconds" : 8.227,
    "loopBeats" : 8.0,
    "tempo" : 120.0,
    "intensity" : 0.5,
    "event" : "PAD",
    "volume" : 1.0,
    "tones" : "B"
  }, {
    "id" : "e87c0240-65fe-400a-aa7f-a900affea474",
    "instrumentId" : "f0c9f024-4f4c-11ed-b752-8bfe000d6dd5",
    "name" : "Gb 7b9",
    "waveformKey" : "Tru-Arpy-Gb-7b9-Gb-7b9.wav",
    "transientSeconds" : 0.0,
    "lengthSeconds" : 8.227,
    "loopBeats" : 8.0,
    "tempo" : 120.0,
    "intensity" : 0.5,
    "event" : "PAD",
    "volume" : 1.0,
    "tones" : "Gb 7b9"
  }, {
    "id" : "4c7d521e-88dd-47be-bd54-ab0c6f7bb960",
    "instrumentId" : "f0c9f024-4f4c-11ed-b752-8bfe000d6dd5",
    "name" : "C maj7",
    "waveformKey" : "Tru-Arpy-C-maj7-C-maj7.wav",
    "transientSeconds" : 0.0,
    "lengthSeconds" : 8.227,
    "loopBeats" : 8.0,
    "tempo" : 120.0,
    "intensity" : 0.5,
    "event" : "PAD",
    "volume" : 1.0,
    "tones" : "C maj7"
  }, {
    "id" : "b39f8270-8c70-49a3-8313-dbb477e4093b",
    "instrumentId" : "f0c9f024-4f4c-11ed-b752-8bfe000d6dd5",
    "name" : "D 7",
    "waveformKey" : "Tru-Arpy-D-7-D-7.wav",
    "transientSeconds" : 0.0,
    "lengthSeconds" : 8.227,
    "loopBeats" : 8.0,
    "tempo" : 120.0,
    "intensity" : 0.5,
    "event" : "PAD",
    "volume" : 1.0,
    "tones" : "D 7"
  }, {
    "id" : "ca3709a3-2b01-426a-8f8d-00bbd631dfbe",
    "instrumentId" : "f0c9f024-4f4c-11ed-b752-8bfe000d6dd5",
    "name" : "A dim7",
    "waveformKey" : "Tru-Arpy-A-dim7-A-dim7.wav",
    "transientSeconds" : 0.0,
    "lengthSeconds" : 8.227,
    "loopBeats" : 8.0,
    "tempo" : 120.0,
    "intensity" : 0.5,
    "event" : "PAD",
    "volume" : 1.0,
    "tones" : "A dim7"
  }, {
    "id" : "e5ea1e47-ec92-405a-82a9-befbc146f537",
    "instrumentId" : "f0c9f024-4f4c-11ed-b752-8bfe000d6dd5",
    "name" : "Eb -7add9",
    "waveformKey" : "Tru-Arpy-Eb--7add9-Eb--7add9.wav",
    "transientSeconds" : 0.0,
    "lengthSeconds" : 6.178999,
    "loopBeats" : 8.0,
    "tempo" : 120.0,
    "intensity" : 0.5,
    "event" : "PAD",
    "volume" : 1.0,
    "tones" : "Eb -7add9"
  }, {
    "id" : "cbe91810-a003-4879-9e35-706c267d6ae0",
    "instrumentId" : "f0c9f024-4f4c-11ed-b752-8bfe000d6dd5",
    "name" : "D maj7add9",
    "waveformKey" : "Tru-Arpy-D-maj7add9-D-maj7add9.wav",
    "transientSeconds" : 0.0,
    "lengthSeconds" : 8.227,
    "loopBeats" : 8.0,
    "tempo" : 120.0,
    "intensity" : 0.5,
    "event" : "PAD",
    "volume" : 1.0,
    "tones" : "D maj7add9"
  }, {
    "id" : "4bb5a767-3220-4daa-a0b5-da740341de91",
    "instrumentId" : "f0c9f024-4f4c-11ed-b752-8bfe000d6dd5",
    "name" : "A sus2",
    "waveformKey" : "Tru-Arpy-A-sus2-A-sus2.wav",
    "transientSeconds" : 0.0,
    "lengthSeconds" : 8.227,
    "loopBeats" : 8.0,
    "tempo" : 120.0,
    "intensity" : 0.5,
    "event" : "PAD",
    "volume" : 1.0,
    "tones" : "A sus2"
  }, {
    "id" : "48c23fe8-7845-48d9-8cf2-5b9434ce3f55",
    "instrumentId" : "f0c9f024-4f4c-11ed-b752-8bfe000d6dd5",
    "name" : "Gb min",
    "waveformKey" : "Tru-Arpy-Gb-min-Gb--.wav",
    "transientSeconds" : 0.0,
    "lengthSeconds" : 8.227,
    "loopBeats" : 8.0,
    "tempo" : 120.0,
    "intensity" : 0.5,
    "event" : "PAD",
    "volume" : 1.0,
    "tones" : "Gb -"
  }, {
    "id" : "7e2eea82-49ea-4bac-8c04-f22dd00e0a83",
    "instrumentId" : "f0c9f024-4f4c-11ed-b752-8bfe000d6dd5",
    "name" : "Gb aug7",
    "waveformKey" : "Tru-Arpy-Gb-aug7-Gb-aug7.wav",
    "transientSeconds" : 0.0,
    "lengthSeconds" : 8.227,
    "loopBeats" : 8.0,
    "tempo" : 120.0,
    "intensity" : 0.5,
    "event" : "PAD",
    "volume" : 1.0,
    "tones" : "Gb aug7"
  }, {
    "id" : "cccbee47-fbd0-49b0-b0ea-45ba93e9c204",
    "instrumentId" : "f0c9f024-4f4c-11ed-b752-8bfe000d6dd5",
    "name" : "F",
    "waveformKey" : "Tru-Arpy-F-F.wav",
    "transientSeconds" : 0.0,
    "lengthSeconds" : 8.227,
    "loopBeats" : 8.0,
    "tempo" : 120.0,
    "intensity" : 0.5,
    "event" : "PAD",
    "volume" : 1.0,
    "tones" : "F"
  }, {
    "id" : "3cf8c423-1206-41ea-b08c-1a934f3f2844",
    "instrumentId" : "f0c9f024-4f4c-11ed-b752-8bfe000d6dd5",
    "name" : "Bb -7add9",
    "waveformKey" : "Tru-Arpy-Bb--7add9-Bb--7add9.wav",
    "transientSeconds" : 0.0,
    "lengthSeconds" : 8.227,
    "loopBeats" : 8.0,
    "tempo" : 120.0,
    "intensity" : 0.5,
    "event" : "PAD",
    "volume" : 1.0,
    "tones" : "Bb -7add9"
  }, {
    "id" : "74eaa369-0756-4a3f-992f-e9e3ca66c215",
    "instrumentId" : "f0c9f024-4f4c-11ed-b752-8bfe000d6dd5",
    "name" : "Eb aug7",
    "waveformKey" : "Tru-Arpy-Eb-aug7-Eb-aug7.wav",
    "transientSeconds" : 0.0,
    "lengthSeconds" : 8.227,
    "loopBeats" : 8.0,
    "tempo" : 120.0,
    "intensity" : 0.5,
    "event" : "PAD",
    "volume" : 1.0,
    "tones" : "Eb aug7"
  }, {
    "id" : "cfec443c-4f8f-4b29-88c9-9c0e3d97f873",
    "instrumentId" : "f0c9f024-4f4c-11ed-b752-8bfe000d6dd5",
    "name" : "Gb 7sus4",
    "waveformKey" : "Tru-Arpy-Gb-7sus4-Gb-7sus4.wav",
    "transientSeconds" : 0.0,
    "lengthSeconds" : 8.227,
    "loopBeats" : 8.0,
    "tempo" : 120.0,
    "intensity" : 0.5,
    "event" : "PAD",
    "volume" : 1.0,
    "tones" : "Gb 7sus4"
  }, {
    "id" : "488ce508-72df-4e7c-9074-df45d574f937",
    "instrumentId" : "f0c9f024-4f4c-11ed-b752-8bfe000d6dd5",
    "name" : "Gb -7b5",
    "waveformKey" : "Tru-Arpy-Gb--7b5-Gb--7b5.wav",
    "transientSeconds" : 0.0,
    "lengthSeconds" : 8.227,
    "loopBeats" : 8.0,
    "tempo" : 120.0,
    "intensity" : 0.5,
    "event" : "PAD",
    "volume" : 1.0,
    "tones" : "Gb -7b5"
  }, {
    "id" : "4075c9d3-9ba0-4673-b3d1-497a69e7406f",
    "instrumentId" : "f0c9f024-4f4c-11ed-b752-8bfe000d6dd5",
    "name" : "Eb dim",
    "waveformKey" : "Tru-Arpy-Eb-dim-Eb-dim.wav",
    "transientSeconds" : 0.0,
    "lengthSeconds" : 8.227,
    "loopBeats" : 8.0,
    "tempo" : 120.0,
    "intensity" : 0.5,
    "event" : "PAD",
    "volume" : 1.0,
    "tones" : "Eb dim"
  }, {
    "id" : "14583d1c-7e8f-4a14-8b21-b29d32f53aca",
    "instrumentId" : "f0c9f024-4f4c-11ed-b752-8bfe000d6dd5",
    "name" : "A",
    "waveformKey" : "Tru-Arpy-A-A.wav",
    "transientSeconds" : 0.0,
    "lengthSeconds" : 8.227,
    "loopBeats" : 8.0,
    "tempo" : 120.0,
    "intensity" : 0.5,
    "event" : "PAD",
    "volume" : 1.0,
    "tones" : "A"
  }, {
    "id" : "045876da-cec9-4df2-b810-dac740ee5ddf",
    "instrumentId" : "f0c9f024-4f4c-11ed-b752-8bfe000d6dd5",
    "name" : "A maj7",
    "waveformKey" : "Tru-Arpy-A-maj7-A-maj7.wav",
    "transientSeconds" : 0.0,
    "lengthSeconds" : 8.227,
    "loopBeats" : 8.0,
    "tempo" : 120.0,
    "intensity" : 0.5,
    "event" : "PAD",
    "volume" : 1.0,
    "tones" : "A maj7"
  }, {
    "id" : "2267d4b4-3bc5-4405-8aab-d9f058907887",
    "instrumentId" : "f0c9f024-4f4c-11ed-b752-8bfe000d6dd5",
    "name" : "Ab maj7",
    "waveformKey" : "Tru-Arpy-Ab-maj7-Ab-maj7.wav",
    "transientSeconds" : 0.0,
    "lengthSeconds" : 8.227,
    "loopBeats" : 8.0,
    "tempo" : 120.0,
    "intensity" : 0.5,
    "event" : "PAD",
    "volume" : 1.0,
    "tones" : "Ab maj7"
  }, {
    "id" : "baf174ee-22f8-43f4-95a4-ac568e2851a8",
    "instrumentId" : "f0c9f024-4f4c-11ed-b752-8bfe000d6dd5",
    "name" : "Db maj7add9",
    "waveformKey" : "Tru-Arpy-Db-maj7add9-Db-maj7add9.wav",
    "transientSeconds" : 0.0,
    "lengthSeconds" : 8.227,
    "loopBeats" : 8.0,
    "tempo" : 120.0,
    "intensity" : 0.5,
    "event" : "PAD",
    "volume" : 1.0,
    "tones" : "Db maj7add9"
  }, {
    "id" : "e0dfd725-7227-428c-add2-14374fe00235",
    "instrumentId" : "f0c9f024-4f4c-11ed-b752-8bfe000d6dd5",
    "name" : "E -7b5",
    "waveformKey" : "Tru-Arpy-E--7b5-E--7b5.wav",
    "transientSeconds" : 0.0,
    "lengthSeconds" : 8.227,
    "loopBeats" : 8.0,
    "tempo" : 120.0,
    "intensity" : 0.5,
    "event" : "PAD",
    "volume" : 1.0,
    "tones" : "E -7b5"
  }, {
    "id" : "88f0fefc-71f7-488f-924e-6f959ae3612e",
    "instrumentId" : "f0c9f024-4f4c-11ed-b752-8bfe000d6dd5",
    "name" : "F maj7add9",
    "waveformKey" : "Tru-Arpy-F-maj7add9-F-maj7add9.wav",
    "transientSeconds" : 0.0,
    "lengthSeconds" : 8.227,
    "loopBeats" : 8.0,
    "tempo" : 120.0,
    "intensity" : 0.5,
    "event" : "PAD",
    "volume" : 1.0,
    "tones" : "F maj7add9"
  }, {
    "id" : "31256bbc-0a0a-47f4-babf-94858125011b",
    "instrumentId" : "f0c9f024-4f4c-11ed-b752-8bfe000d6dd5",
    "name" : "Eb dim7",
    "waveformKey" : "Tru-Arpy-Eb-dim7-Eb-dim7.wav",
    "transientSeconds" : 0.0,
    "lengthSeconds" : 8.227,
    "loopBeats" : 8.0,
    "tempo" : 120.0,
    "intensity" : 0.5,
    "event" : "PAD",
    "volume" : 1.0,
    "tones" : "Eb dim7"
  }, {
    "id" : "0c4fea1a-a287-4f2f-8e5f-8abff56ece16",
    "instrumentId" : "f0c9f024-4f4c-11ed-b752-8bfe000d6dd5",
    "name" : "Db min",
    "waveformKey" : "Tru-Arpy-Db-min-Db--.wav",
    "transientSeconds" : 0.0,
    "lengthSeconds" : 8.227,
    "loopBeats" : 8.0,
    "tempo" : 120.0,
    "intensity" : 0.5,
    "event" : "PAD",
    "volume" : 1.0,
    "tones" : "Db -"
  }, {
    "id" : "fdbebb41-5bc3-43d4-9428-21e879685f27",
    "instrumentId" : "f0c9f024-4f4c-11ed-b752-8bfe000d6dd5",
    "name" : "Ab 7sus4",
    "waveformKey" : "Tru-Arpy-Ab-7sus4-Ab-7sus4.wav",
    "transientSeconds" : 0.0,
    "lengthSeconds" : 8.227,
    "loopBeats" : 8.0,
    "tempo" : 120.0,
    "intensity" : 0.5,
    "event" : "PAD",
    "volume" : 1.0,
    "tones" : "Ab 7sus4"
  }, {
    "id" : "c52bc33f-2107-4c40-af37-6ceb6e2d4fc5",
    "instrumentId" : "f0c9f024-4f4c-11ed-b752-8bfe000d6dd5",
    "name" : "A aug7",
    "waveformKey" : "Tru-Arpy-A-aug7-A-aug7.wav",
    "transientSeconds" : 0.0,
    "lengthSeconds" : 8.227,
    "loopBeats" : 8.0,
    "tempo" : 120.0,
    "intensity" : 0.5,
    "event" : "PAD",
    "volume" : 1.0,
    "tones" : "A aug7"
  }, {
    "id" : "feb192cd-0013-4300-80ef-1c69d34db2cc",
    "instrumentId" : "f0c9f024-4f4c-11ed-b752-8bfe000d6dd5",
    "name" : "Eb 7sus4",
    "waveformKey" : "Tru-Arpy-Eb-7sus4-Eb-7sus4.wav",
    "transientSeconds" : 0.0,
    "lengthSeconds" : 6.178999,
    "loopBeats" : 8.0,
    "tempo" : 120.0,
    "intensity" : 0.5,
    "event" : "PAD",
    "volume" : 1.0,
    "tones" : "Eb 7sus4"
  }, {
    "id" : "12488066-33d5-48df-a607-efb50dd1872f",
    "instrumentId" : "f0c9f024-4f4c-11ed-b752-8bfe000d6dd5",
    "name" : "C -7",
    "waveformKey" : "Tru-Arpy-C--7-C--7.wav",
    "transientSeconds" : 0.0,
    "lengthSeconds" : 8.227,
    "loopBeats" : 8.0,
    "tempo" : 120.0,
    "intensity" : 0.5,
    "event" : "PAD",
    "volume" : 1.0,
    "tones" : "C -7"
  }, {
    "id" : "df2d4b39-d5c2-455f-9c62-1e682a4db4a7",
    "instrumentId" : "f0c9f024-4f4c-11ed-b752-8bfe000d6dd5",
    "name" : "D 7sus4",
    "waveformKey" : "Tru-Arpy-D-7sus4-D-7sus4.wav",
    "transientSeconds" : 0.0,
    "lengthSeconds" : 8.227,
    "loopBeats" : 8.0,
    "tempo" : 120.0,
    "intensity" : 0.5,
    "event" : "PAD",
    "volume" : 1.0,
    "tones" : "D 7sus4"
  }, {
    "id" : "a9778a6c-5c8b-4f61-8f7b-28e216b4a1b6",
    "instrumentId" : "f0c9f024-4f4c-11ed-b752-8bfe000d6dd5",
    "name" : "Ab dim7",
    "waveformKey" : "Tru-Arpy-Ab-dim7-Ab-dim7.wav",
    "transientSeconds" : 0.0,
    "lengthSeconds" : 8.227,
    "loopBeats" : 8.0,
    "tempo" : 120.0,
    "intensity" : 0.5,
    "event" : "PAD",
    "volume" : 1.0,
    "tones" : "Ab dim7"
  }, {
    "id" : "36dffda3-d2de-4a58-a3d3-4d3057b053c3",
    "instrumentId" : "f0c9f024-4f4c-11ed-b752-8bfe000d6dd5",
    "name" : "Gb 7",
    "waveformKey" : "Tru-Arpy-Gb-7-Gb-7.wav",
    "transientSeconds" : 0.0,
    "lengthSeconds" : 8.227,
    "loopBeats" : 8.0,
    "tempo" : 120.0,
    "intensity" : 0.5,
    "event" : "PAD",
    "volume" : 1.0,
    "tones" : "Gb 7"
  }, {
    "id" : "4f25f5e0-e69d-4a8b-8a8a-94eb7f873e5f",
    "instrumentId" : "f0c9f024-4f4c-11ed-b752-8bfe000d6dd5",
    "name" : "D dim",
    "waveformKey" : "Tru-Arpy-D-dim-D-dim.wav",
    "transientSeconds" : 0.0,
    "lengthSeconds" : 8.227,
    "loopBeats" : 8.0,
    "tempo" : 120.0,
    "intensity" : 0.5,
    "event" : "PAD",
    "volume" : 1.0,
    "tones" : "D dim"
  }, {
    "id" : "2d86f828-b838-43d7-b808-c70a6927390f",
    "instrumentId" : "f0c9f024-4f4c-11ed-b752-8bfe000d6dd5",
    "name" : "Ab -7b5",
    "waveformKey" : "Tru-Arpy-Ab--7b5-Ab--7b5.wav",
    "transientSeconds" : 0.0,
    "lengthSeconds" : 8.227,
    "loopBeats" : 8.0,
    "tempo" : 120.0,
    "intensity" : 0.5,
    "event" : "PAD",
    "volume" : 1.0,
    "tones" : "Ab -7b5"
  }, {
    "id" : "a8c05ccd-93cd-4e78-a234-9b51836192d1",
    "instrumentId" : "f0c9f024-4f4c-11ed-b752-8bfe000d6dd5",
    "name" : "Bb sus4",
    "waveformKey" : "Tru-Arpy-Bb-sus4-Bb-sus4.wav",
    "transientSeconds" : 0.0,
    "lengthSeconds" : 8.227,
    "loopBeats" : 8.0,
    "tempo" : 120.0,
    "intensity" : 0.5,
    "event" : "PAD",
    "volume" : 1.0,
    "tones" : "Bb sus4"
  }, {
    "id" : "ce800413-862e-41ab-8db9-773b8b5742ae",
    "instrumentId" : "f0c9f024-4f4c-11ed-b752-8bfe000d6dd5",
    "name" : "Bb aug7",
    "waveformKey" : "Tru-Arpy-Bb-aug7-Bb-aug7.wav",
    "transientSeconds" : 0.0,
    "lengthSeconds" : 8.227,
    "loopBeats" : 8.0,
    "tempo" : 120.0,
    "intensity" : 0.5,
    "event" : "PAD",
    "volume" : 1.0,
    "tones" : "Bb aug7"
  }, {
    "id" : "061c62ab-b8fc-413d-b2fe-46352dacf97f",
    "instrumentId" : "f0c9f024-4f4c-11ed-b752-8bfe000d6dd5",
    "name" : "Gb dim",
    "waveformKey" : "Tru-Arpy-Gb-dim-Gb-dim.wav",
    "transientSeconds" : 0.0,
    "lengthSeconds" : 8.227,
    "loopBeats" : 8.0,
    "tempo" : 120.0,
    "intensity" : 0.5,
    "event" : "PAD",
    "volume" : 1.0,
    "tones" : "Gb dim"
  }, {
    "id" : "aa297463-31d3-48d2-84b6-1c686040b8bb",
    "instrumentId" : "f0c9f024-4f4c-11ed-b752-8bfe000d6dd5",
    "name" : "A -7",
    "waveformKey" : "Tru-Arpy-A--7-A--7.wav",
    "transientSeconds" : 0.0,
    "lengthSeconds" : 8.227,
    "loopBeats" : 8.0,
    "tempo" : 120.0,
    "intensity" : 0.5,
    "event" : "PAD",
    "volume" : 1.0,
    "tones" : "A -7"
  }, {
    "id" : "55c33322-73ba-47fd-903e-9e58d984d036",
    "instrumentId" : "f0c9f024-4f4c-11ed-b752-8bfe000d6dd5",
    "name" : "B -7b5",
    "waveformKey" : "Tru-Arpy-B--7b5-B--7b5.wav",
    "transientSeconds" : 0.0,
    "lengthSeconds" : 8.227,
    "loopBeats" : 8.0,
    "tempo" : 120.0,
    "intensity" : 0.5,
    "event" : "PAD",
    "volume" : 1.0,
    "tones" : "B -7b5"
  }, {
    "id" : "72c6469e-1d54-4507-8fd5-46c807b0e3d2",
    "instrumentId" : "f0c9f024-4f4c-11ed-b752-8bfe000d6dd5",
    "name" : "Eb 7",
    "waveformKey" : "Tru-Arpy-Eb-7-Eb-7.wav",
    "transientSeconds" : 0.0,
    "lengthSeconds" : 8.227,
    "loopBeats" : 8.0,
    "tempo" : 120.0,
    "intensity" : 0.5,
    "event" : "PAD",
    "volume" : 1.0,
    "tones" : "Eb 7"
  }, {
    "id" : "770760df-0520-4c4e-940f-76bdb0b12ac3",
    "instrumentId" : "f0c9f024-4f4c-11ed-b752-8bfe000d6dd5",
    "name" : "Db dim7",
    "waveformKey" : "Tru-Arpy-Db-dim7-Db-dim7.wav",
    "transientSeconds" : 0.0,
    "lengthSeconds" : 8.227,
    "loopBeats" : 8.0,
    "tempo" : 120.0,
    "intensity" : 0.5,
    "event" : "PAD",
    "volume" : 1.0,
    "tones" : "Db dim7"
  }, {
    "id" : "4eea9754-355f-4f19-ba1b-706366f3d10b",
    "instrumentId" : "f0c9f024-4f4c-11ed-b752-8bfe000d6dd5",
    "name" : "F maj7",
    "waveformKey" : "Tru-Arpy-F-maj7-F-maj7.wav",
    "transientSeconds" : 0.0,
    "lengthSeconds" : 8.227,
    "loopBeats" : 8.0,
    "tempo" : 120.0,
    "intensity" : 0.5,
    "event" : "PAD",
    "volume" : 1.0,
    "tones" : "F maj7"
  }, {
    "id" : "58e4054f-ae01-423a-ad74-7f9eea735371",
    "instrumentId" : "f0c9f024-4f4c-11ed-b752-8bfe000d6dd5",
    "name" : "F -7",
    "waveformKey" : "Tru-Arpy-F--7-F--7.wav",
    "transientSeconds" : 0.0,
    "lengthSeconds" : 8.227,
    "loopBeats" : 8.0,
    "tempo" : 120.0,
    "intensity" : 0.5,
    "event" : "PAD",
    "volume" : 1.0,
    "tones" : "F -7"
  }, {
    "id" : "057ed949-2a8f-4fa7-ba73-5883dbb9932f",
    "instrumentId" : "f0c9f024-4f4c-11ed-b752-8bfe000d6dd5",
    "name" : "G",
    "waveformKey" : "Tru-Arpy-G-G.wav",
    "transientSeconds" : 0.0,
    "lengthSeconds" : 8.227,
    "loopBeats" : 8.0,
    "tempo" : 120.0,
    "intensity" : 0.5,
    "event" : "PAD",
    "volume" : 1.0,
    "tones" : "G"
  }, {
    "id" : "25e89eaf-70d2-4308-a90a-159c00124763",
    "instrumentId" : "f0c9f024-4f4c-11ed-b752-8bfe000d6dd5",
    "name" : "G dim7",
    "waveformKey" : "Tru-Arpy-G-dim7-G-dim7.wav",
    "transientSeconds" : 0.0,
    "lengthSeconds" : 8.227,
    "loopBeats" : 8.0,
    "tempo" : 120.0,
    "intensity" : 0.5,
    "event" : "PAD",
    "volume" : 1.0,
    "tones" : "G dim7"
  }, {
    "id" : "083474dd-d9b3-4419-9dd9-0f68186775e8",
    "instrumentId" : "f0c9f024-4f4c-11ed-b752-8bfe000d6dd5",
    "name" : "A aug",
    "waveformKey" : "Tru-Arpy-A-aug-A-aug.wav",
    "transientSeconds" : 0.0,
    "lengthSeconds" : 8.227,
    "loopBeats" : 8.0,
    "tempo" : 120.0,
    "intensity" : 0.5,
    "event" : "PAD",
    "volume" : 1.0,
    "tones" : "A aug"
  }, {
    "id" : "d455aab1-041d-4d2e-a16d-7aa7e8fca39c",
    "instrumentId" : "f0c9f024-4f4c-11ed-b752-8bfe000d6dd5",
    "name" : "G min",
    "waveformKey" : "Tru-Arpy-G-min-G--.wav",
    "transientSeconds" : 0.0,
    "lengthSeconds" : 8.227,
    "loopBeats" : 8.0,
    "tempo" : 120.0,
    "intensity" : 0.5,
    "event" : "PAD",
    "volume" : 1.0,
    "tones" : "G -"
  }, {
    "id" : "2d25bf43-b914-40ec-8a41-50a38cb0384c",
    "instrumentId" : "f0c9f024-4f4c-11ed-b752-8bfe000d6dd5",
    "name" : "A 7sus4",
    "waveformKey" : "Tru-Arpy-A-7sus4-A-7sus4.wav",
    "transientSeconds" : 0.0,
    "lengthSeconds" : 8.227,
    "loopBeats" : 8.0,
    "tempo" : 120.0,
    "intensity" : 0.5,
    "event" : "PAD",
    "volume" : 1.0,
    "tones" : "A 7sus4"
  }, {
    "id" : "13d6b364-2bf0-4e4b-95ae-8635d0a64fb6",
    "instrumentId" : "f0c9f024-4f4c-11ed-b752-8bfe000d6dd5",
    "name" : "G maj7",
    "waveformKey" : "Tru-Arpy-G-maj7-G-maj7.wav",
    "transientSeconds" : 0.0,
    "lengthSeconds" : 8.227,
    "loopBeats" : 8.0,
    "tempo" : 120.0,
    "intensity" : 0.5,
    "event" : "PAD",
    "volume" : 1.0,
    "tones" : "G maj7"
  }, {
    "id" : "cf2ad869-ac48-42e2-9800-221681035479",
    "instrumentId" : "f0c9f024-4f4c-11ed-b752-8bfe000d6dd5",
    "name" : "E 7b9",
    "waveformKey" : "Tru-Arpy-E-7b9-E-7b9.wav",
    "transientSeconds" : 0.0,
    "lengthSeconds" : 8.227,
    "loopBeats" : 8.0,
    "tempo" : 120.0,
    "intensity" : 0.5,
    "event" : "PAD",
    "volume" : 1.0,
    "tones" : "E 7b9"
  }, {
    "id" : "5969b100-1f00-4c43-8e9a-4b2918c8d8d8",
    "instrumentId" : "f0c9f024-4f4c-11ed-b752-8bfe000d6dd5",
    "name" : "D -7b5",
    "waveformKey" : "Tru-Arpy-D--7b5-D--7b5.wav",
    "transientSeconds" : 0.0,
    "lengthSeconds" : 8.227,
    "loopBeats" : 8.0,
    "tempo" : 120.0,
    "intensity" : 0.5,
    "event" : "PAD",
    "volume" : 1.0,
    "tones" : "D -7b5"
  }, {
    "id" : "3ee16688-6527-49ea-a5bb-c8210df8074f",
    "instrumentId" : "f0c9f024-4f4c-11ed-b752-8bfe000d6dd5",
    "name" : "Bb",
    "waveformKey" : "Tru-Arpy-Bb-Bb.wav",
    "transientSeconds" : 0.0,
    "lengthSeconds" : 8.227,
    "loopBeats" : 8.0,
    "tempo" : 120.0,
    "intensity" : 0.5,
    "event" : "PAD",
    "volume" : 1.0,
    "tones" : "Bb"
  }, {
    "id" : "f56bc9b2-29a5-4d19-ad9a-18f0223da5b9",
    "instrumentId" : "f0c9f024-4f4c-11ed-b752-8bfe000d6dd5",
    "name" : "B maj7add9",
    "waveformKey" : "Tru-Arpy-B-maj7add9-B-maj7add9.wav",
    "transientSeconds" : 0.0,
    "lengthSeconds" : 8.227,
    "loopBeats" : 8.0,
    "tempo" : 120.0,
    "intensity" : 0.5,
    "event" : "PAD",
    "volume" : 1.0,
    "tones" : "B maj7add9"
  }, {
    "id" : "25cbf0b0-b864-4901-9202-2b913c767177",
    "instrumentId" : "f0c9f024-4f4c-11ed-b752-8bfe000d6dd5",
    "name" : "Gb aug",
    "waveformKey" : "Tru-Arpy-Gb-aug-Gb-aug.wav",
    "transientSeconds" : 0.0,
    "lengthSeconds" : 8.227,
    "loopBeats" : 8.0,
    "tempo" : 120.0,
    "intensity" : 0.5,
    "event" : "PAD",
    "volume" : 1.0,
    "tones" : "Gb aug"
  }, {
    "id" : "fcb0dff4-4086-4644-9fd7-2e6f8179b2cb",
    "instrumentId" : "f0c9f024-4f4c-11ed-b752-8bfe000d6dd5",
    "name" : "F -7b5",
    "waveformKey" : "Tru-Arpy-F--7b5-F--7b5.wav",
    "transientSeconds" : 0.0,
    "lengthSeconds" : 8.227,
    "loopBeats" : 8.0,
    "tempo" : 120.0,
    "intensity" : 0.5,
    "event" : "PAD",
    "volume" : 1.0,
    "tones" : "F -7b5"
  }, {
    "id" : "37d9052d-fd2d-49f7-8a74-66b5bf17e769",
    "instrumentId" : "f0c9f024-4f4c-11ed-b752-8bfe000d6dd5",
    "name" : "Db maj7",
    "waveformKey" : "Tru-Arpy-Db-maj7-Db-maj7.wav",
    "transientSeconds" : 0.0,
    "lengthSeconds" : 8.227,
    "loopBeats" : 8.0,
    "tempo" : 120.0,
    "intensity" : 0.5,
    "event" : "PAD",
    "volume" : 1.0,
    "tones" : "Db maj7"
  }, {
    "id" : "3fea48c4-de2d-40ce-b92a-7edf8536a79c",
    "instrumentId" : "f0c9f024-4f4c-11ed-b752-8bfe000d6dd5",
    "name" : "D maj7",
    "waveformKey" : "Tru-Arpy-D-maj7-D-maj7.wav",
    "transientSeconds" : 0.0,
    "lengthSeconds" : 8.227,
    "loopBeats" : 8.0,
    "tempo" : 120.0,
    "intensity" : 0.5,
    "event" : "PAD",
    "volume" : 1.0,
    "tones" : "D maj7"
  }, {
    "id" : "5bc85f0c-18aa-4297-9bb3-d3871bbb58e4",
    "instrumentId" : "f0c9f024-4f4c-11ed-b752-8bfe000d6dd5",
    "name" : "F aug7",
    "waveformKey" : "Tru-Arpy-F-aug7-F-aug7.wav",
    "transientSeconds" : 0.0,
    "lengthSeconds" : 8.227,
    "loopBeats" : 8.0,
    "tempo" : 120.0,
    "intensity" : 0.5,
    "event" : "PAD",
    "volume" : 1.0,
    "tones" : "F aug7"
  }, {
    "id" : "a291f3b7-50d3-4c2a-92ff-1f0bb13d8d85",
    "instrumentId" : "f0c9f024-4f4c-11ed-b752-8bfe000d6dd5",
    "name" : "Gb sus4",
    "waveformKey" : "Tru-Arpy-Gb-sus4-Gb-sus4.wav",
    "transientSeconds" : 0.0,
    "lengthSeconds" : 8.227,
    "loopBeats" : 8.0,
    "tempo" : 120.0,
    "intensity" : 0.5,
    "event" : "PAD",
    "volume" : 1.0,
    "tones" : "Gb sus4"
  }, {
    "id" : "0fc8c827-9442-4123-a295-2bf5989ee9e3",
    "instrumentId" : "f0c9f024-4f4c-11ed-b752-8bfe000d6dd5",
    "name" : "B aug7",
    "waveformKey" : "Tru-Arpy-B-aug7-B-aug7.wav",
    "transientSeconds" : 0.0,
    "lengthSeconds" : 8.227,
    "loopBeats" : 8.0,
    "tempo" : 120.0,
    "intensity" : 0.5,
    "event" : "PAD",
    "volume" : 1.0,
    "tones" : "B aug7"
  }, {
    "id" : "33b689fb-5429-4071-aa72-19db3022010a",
    "instrumentId" : "f0c9f024-4f4c-11ed-b752-8bfe000d6dd5",
    "name" : "D dim7",
    "waveformKey" : "Tru-Arpy-D-dim7-D-dim7.wav",
    "transientSeconds" : 0.0,
    "lengthSeconds" : 8.227,
    "loopBeats" : 8.0,
    "tempo" : 120.0,
    "intensity" : 0.5,
    "event" : "PAD",
    "volume" : 1.0,
    "tones" : "D dim7"
  }, {
    "id" : "0db475e4-6ee2-42fa-8d80-494dd3337b22",
    "instrumentId" : "f0c9f024-4f4c-11ed-b752-8bfe000d6dd5",
    "name" : "B 7",
    "waveformKey" : "Tru-Arpy-B-7-B-7.wav",
    "transientSeconds" : 0.0,
    "lengthSeconds" : 8.227,
    "loopBeats" : 8.0,
    "tempo" : 120.0,
    "intensity" : 0.5,
    "event" : "PAD",
    "volume" : 1.0,
    "tones" : "B 7"
  }, {
    "id" : "3ed54a99-5c6b-4be7-a991-f3a65ac3a6a1",
    "instrumentId" : "f0c9f024-4f4c-11ed-b752-8bfe000d6dd5",
    "name" : "E maj7add9",
    "waveformKey" : "Tru-Arpy-E-maj7add9-E-maj7add9.wav",
    "transientSeconds" : 0.0,
    "lengthSeconds" : 8.227,
    "loopBeats" : 8.0,
    "tempo" : 120.0,
    "intensity" : 0.5,
    "event" : "PAD",
    "volume" : 1.0,
    "tones" : "E maj7add9"
  }, {
    "id" : "b52faa7c-416e-4d58-a40a-040d5ea56950",
    "instrumentId" : "f0c9f024-4f4c-11ed-b752-8bfe000d6dd5",
    "name" : "E dim7",
    "waveformKey" : "Tru-Arpy-E-dim7-E-dim7.wav",
    "transientSeconds" : 0.0,
    "lengthSeconds" : 8.227,
    "loopBeats" : 8.0,
    "tempo" : 120.0,
    "intensity" : 0.5,
    "event" : "PAD",
    "volume" : 1.0,
    "tones" : "E dim7"
  }, {
    "id" : "36065c90-4ed2-4f05-a780-567740826fa3",
    "instrumentId" : "f0c9f024-4f4c-11ed-b752-8bfe000d6dd5",
    "name" : "B sus2",
    "waveformKey" : "Tru-Arpy-B-sus2-B-sus2.wav",
    "transientSeconds" : 0.0,
    "lengthSeconds" : 8.227,
    "loopBeats" : 8.0,
    "tempo" : 120.0,
    "intensity" : 0.5,
    "event" : "PAD",
    "volume" : 1.0,
    "tones" : "B sus2"
  }, {
    "id" : "17ce317c-79ca-4aaf-95c5-6cafecaa288e",
    "instrumentId" : "f0c9f024-4f4c-11ed-b752-8bfe000d6dd5",
    "name" : "A sus4",
    "waveformKey" : "Tru-Arpy-A-sus4-A-sus4.wav",
    "transientSeconds" : 0.0,
    "lengthSeconds" : 8.227,
    "loopBeats" : 8.0,
    "tempo" : 120.0,
    "intensity" : 0.5,
    "event" : "PAD",
    "volume" : 1.0,
    "tones" : "A sus4"
  }, {
    "id" : "7fdbab7f-ffbe-4e5c-b79a-a6266e978df6",
    "instrumentId" : "f0c9f024-4f4c-11ed-b752-8bfe000d6dd5",
    "name" : "Bb aug",
    "waveformKey" : "Tru-Arpy-Bb-aug-Bb-aug.wav",
    "transientSeconds" : 0.0,
    "lengthSeconds" : 8.227,
    "loopBeats" : 8.0,
    "tempo" : 120.0,
    "intensity" : 0.5,
    "event" : "PAD",
    "volume" : 1.0,
    "tones" : "Bb aug"
  }, {
    "id" : "28edb77b-03f0-47be-9f7b-f407eaf261cd",
    "instrumentId" : "f0c9f024-4f4c-11ed-b752-8bfe000d6dd5",
    "name" : "Db sus2",
    "waveformKey" : "Tru-Arpy-Db-sus2-Db-sus2.wav",
    "transientSeconds" : 0.0,
    "lengthSeconds" : 8.227,
    "loopBeats" : 8.0,
    "tempo" : 120.0,
    "intensity" : 0.5,
    "event" : "PAD",
    "volume" : 1.0,
    "tones" : "Db sus2"
  }, {
    "id" : "5b148de0-334c-4139-a154-e416f2910bcd",
    "instrumentId" : "f0c9f024-4f4c-11ed-b752-8bfe000d6dd5",
    "name" : "Ab sus4",
    "waveformKey" : "Tru-Arpy-Ab-sus4-Ab-sus4.wav",
    "transientSeconds" : 0.0,
    "lengthSeconds" : 8.227,
    "loopBeats" : 8.0,
    "tempo" : 120.0,
    "intensity" : 0.5,
    "event" : "PAD",
    "volume" : 1.0,
    "tones" : "Ab sus4"
  }, {
    "id" : "12ae44b0-4320-43ac-a41f-761f9cfa85c9",
    "instrumentId" : "f0c9f024-4f4c-11ed-b752-8bfe000d6dd5",
    "name" : "F 7sus4",
    "waveformKey" : "Tru-Arpy-F-7sus4-F-7sus4.wav",
    "transientSeconds" : 0.0,
    "lengthSeconds" : 8.227,
    "loopBeats" : 8.0,
    "tempo" : 120.0,
    "intensity" : 0.5,
    "event" : "PAD",
    "volume" : 1.0,
    "tones" : "F 7sus4"
  }, {
    "id" : "c9a09d37-0d7b-4302-b48f-336a6f646fcc",
    "instrumentId" : "f0c9f024-4f4c-11ed-b752-8bfe000d6dd5",
    "name" : "A 7",
    "waveformKey" : "Tru-Arpy-A-7-A-7.wav",
    "transientSeconds" : 0.0,
    "lengthSeconds" : 8.227,
    "loopBeats" : 8.0,
    "tempo" : 120.0,
    "intensity" : 0.5,
    "event" : "PAD",
    "volume" : 1.0,
    "tones" : "A 7"
  }, {
    "id" : "d5d7b869-9939-4508-b7e1-afb47ff4e98d",
    "instrumentId" : "f0c9f024-4f4c-11ed-b752-8bfe000d6dd5",
    "name" : "Bb sus2",
    "waveformKey" : "Tru-Arpy-Bb-sus2-Bb-sus2.wav",
    "transientSeconds" : 0.0,
    "lengthSeconds" : 8.227,
    "loopBeats" : 8.0,
    "tempo" : 120.0,
    "intensity" : 0.5,
    "event" : "PAD",
    "volume" : 1.0,
    "tones" : "Bb sus2"
  }, {
    "id" : "ca731c7a-ea81-4391-8b35-c90127255cac",
    "instrumentId" : "f0c9f024-4f4c-11ed-b752-8bfe000d6dd5",
    "name" : "C",
    "waveformKey" : "Tru-Arpy-C-C.wav",
    "transientSeconds" : 0.0,
    "lengthSeconds" : 8.227,
    "loopBeats" : 8.0,
    "tempo" : 120.0,
    "intensity" : 0.5,
    "event" : "PAD",
    "volume" : 1.0,
    "tones" : "C"
  }, {
    "id" : "c9058961-f634-41c5-aac5-230d1e7a3282",
    "instrumentId" : "f0c9f024-4f4c-11ed-b752-8bfe000d6dd5",
    "name" : "D",
    "waveformKey" : "Tru-Arpy-D-D.wav",
    "transientSeconds" : 0.0,
    "lengthSeconds" : 8.227,
    "loopBeats" : 8.0,
    "tempo" : 120.0,
    "intensity" : 0.5,
    "event" : "PAD",
    "volume" : 1.0,
    "tones" : "D"
  }, {
    "id" : "bdda8885-d175-4032-9f1b-74e2e4089d4c",
    "instrumentId" : "f0c9f024-4f4c-11ed-b752-8bfe000d6dd5",
    "name" : "Gb dim7",
    "waveformKey" : "Tru-Arpy-Gb-dim7-Gb-dim7.wav",
    "transientSeconds" : 0.0,
    "lengthSeconds" : 8.227,
    "loopBeats" : 8.0,
    "tempo" : 120.0,
    "intensity" : 0.5,
    "event" : "PAD",
    "volume" : 1.0,
    "tones" : "Gb dim7"
  }, {
    "id" : "60e645e6-2e1f-4f26-b0b7-6ec74ece2d20",
    "instrumentId" : "f0c9f024-4f4c-11ed-b752-8bfe000d6dd5",
    "name" : "C aug7",
    "waveformKey" : "Tru-Arpy-C-aug7-C-aug7.wav",
    "transientSeconds" : 0.0,
    "lengthSeconds" : 8.227,
    "loopBeats" : 8.0,
    "tempo" : 120.0,
    "intensity" : 0.5,
    "event" : "PAD",
    "volume" : 1.0,
    "tones" : "C aug7"
  }, {
    "id" : "1f075475-636a-45dc-812a-d2251e080e6a",
    "instrumentId" : "f0c9f024-4f4c-11ed-b752-8bfe000d6dd5",
    "name" : "G -7add9",
    "waveformKey" : "Tru-Arpy-G--7add9-G--7add9.wav",
    "transientSeconds" : 0.0,
    "lengthSeconds" : 8.227,
    "loopBeats" : 8.0,
    "tempo" : 120.0,
    "intensity" : 0.5,
    "event" : "PAD",
    "volume" : 1.0,
    "tones" : "G -7add9"
  }, {
    "id" : "dcab0e6c-b929-48ea-a569-04f5a03de00f",
    "instrumentId" : "f0c9f024-4f4c-11ed-b752-8bfe000d6dd5",
    "name" : "B aug",
    "waveformKey" : "Tru-Arpy-B-aug-B-aug.wav",
    "transientSeconds" : 0.0,
    "lengthSeconds" : 8.227,
    "loopBeats" : 8.0,
    "tempo" : 120.0,
    "intensity" : 0.5,
    "event" : "PAD",
    "volume" : 1.0,
    "tones" : "B aug"
  }, {
    "id" : "a10b8fef-b622-4713-8bfd-e33af0f75e4e",
    "instrumentId" : "f0c9f024-4f4c-11ed-b752-8bfe000d6dd5",
    "name" : "E aug",
    "waveformKey" : "Tru-Arpy-E-aug-E-aug.wav",
    "transientSeconds" : 0.0,
    "lengthSeconds" : 8.227,
    "loopBeats" : 8.0,
    "tempo" : 120.0,
    "intensity" : 0.5,
    "event" : "PAD",
    "volume" : 1.0,
    "tones" : "E aug"
  }, {
    "id" : "904fb7d0-45b9-4028-91b7-f2cd5880315f",
    "instrumentId" : "f0c9f024-4f4c-11ed-b752-8bfe000d6dd5",
    "name" : "Bb dim",
    "waveformKey" : "Tru-Arpy-Bb-dim-Bb-dim.wav",
    "transientSeconds" : 0.0,
    "lengthSeconds" : 8.227,
    "loopBeats" : 8.0,
    "tempo" : 120.0,
    "intensity" : 0.5,
    "event" : "PAD",
    "volume" : 1.0,
    "tones" : "Bb dim"
  }, {
    "id" : "d4fe60bc-74de-4172-9a34-38a0489f734e",
    "instrumentId" : "f0c9f024-4f4c-11ed-b752-8bfe000d6dd5",
    "name" : "F sus4",
    "waveformKey" : "Tru-Arpy-F-sus4-F-sus4.wav",
    "transientSeconds" : 0.0,
    "lengthSeconds" : 8.227,
    "loopBeats" : 8.0,
    "tempo" : 120.0,
    "intensity" : 0.5,
    "event" : "PAD",
    "volume" : 1.0,
    "tones" : "F sus4"
  }, {
    "id" : "031a0920-6525-4cad-b84e-bbb35d88566c",
    "instrumentId" : "f0c9f024-4f4c-11ed-b752-8bfe000d6dd5",
    "name" : "Gb",
    "waveformKey" : "Tru-Arpy-Gb-Gb.wav",
    "transientSeconds" : 0.0,
    "lengthSeconds" : 8.227,
    "loopBeats" : 8.0,
    "tempo" : 120.0,
    "intensity" : 0.5,
    "event" : "PAD",
    "volume" : 1.0,
    "tones" : "Gb"
  }, {
    "id" : "2fe6827d-b499-4cc0-9080-c14cd2b9a51b",
    "instrumentId" : "f0c9f024-4f4c-11ed-b752-8bfe000d6dd5",
    "name" : "Ab maj7add9",
    "waveformKey" : "Tru-Arpy-Ab-maj7add9-Ab-maj7add9.wav",
    "transientSeconds" : 0.0,
    "lengthSeconds" : 8.227,
    "loopBeats" : 8.0,
    "tempo" : 120.0,
    "intensity" : 0.5,
    "event" : "PAD",
    "volume" : 1.0,
    "tones" : "Ab maj7add9"
  }, {
    "id" : "d34521f5-53c1-4659-8ee1-6dc3dbff3e5a",
    "instrumentId" : "f0c9f024-4f4c-11ed-b752-8bfe000d6dd5",
    "name" : "Db aug7",
    "waveformKey" : "Tru-Arpy-Db-aug7-Db-aug7.wav",
    "transientSeconds" : 0.0,
    "lengthSeconds" : 8.227,
    "loopBeats" : 8.0,
    "tempo" : 120.0,
    "intensity" : 0.5,
    "event" : "PAD",
    "volume" : 1.0,
    "tones" : "Db aug7"
  }, {
    "id" : "415b780b-fd3c-4dc5-88c2-f66351a85a11",
    "instrumentId" : "f0c9f024-4f4c-11ed-b752-8bfe000d6dd5",
    "name" : "Eb -7",
    "waveformKey" : "Tru-Arpy-Eb--7-Eb--7.wav",
    "transientSeconds" : 0.0,
    "lengthSeconds" : 8.227,
    "loopBeats" : 8.0,
    "tempo" : 120.0,
    "intensity" : 0.5,
    "event" : "PAD",
    "volume" : 1.0,
    "tones" : "Eb -7"
  }, {
    "id" : "2604554f-3faa-4de3-8a3d-aeb2e2b5a689",
    "instrumentId" : "f0c9f024-4f4c-11ed-b752-8bfe000d6dd5",
    "name" : "Bb maj7add9",
    "waveformKey" : "Tru-Arpy-Bb-maj7add9-Bb-maj7add9.wav",
    "transientSeconds" : 0.0,
    "lengthSeconds" : 8.227,
    "loopBeats" : 8.0,
    "tempo" : 120.0,
    "intensity" : 0.5,
    "event" : "PAD",
    "volume" : 1.0,
    "tones" : "Bb maj7add9"
  }, {
    "id" : "838ba657-e667-4014-a600-fae937fc9e0b",
    "instrumentId" : "f0c9f024-4f4c-11ed-b752-8bfe000d6dd5",
    "name" : "Db 7b9",
    "waveformKey" : "Tru-Arpy-Db-7b9-Db-7b9.wav",
    "transientSeconds" : 0.0,
    "lengthSeconds" : 8.227,
    "loopBeats" : 8.0,
    "tempo" : 120.0,
    "intensity" : 0.5,
    "event" : "PAD",
    "volume" : 1.0,
    "tones" : "Db 7b9"
  }, {
    "id" : "96c32cc3-c398-4344-b903-561739d201a8",
    "instrumentId" : "f0c9f024-4f4c-11ed-b752-8bfe000d6dd5",
    "name" : "A min",
    "waveformKey" : "Tru-Arpy-A-min-A--.wav",
    "transientSeconds" : 0.0,
    "lengthSeconds" : 8.227,
    "loopBeats" : 8.0,
    "tempo" : 120.0,
    "intensity" : 0.5,
    "event" : "PAD",
    "volume" : 1.0,
    "tones" : "A -"
  }, {
    "id" : "6ce45c11-717d-4dc2-9c55-a168d3a3a566",
    "instrumentId" : "f0c9f024-4f4c-11ed-b752-8bfe000d6dd5",
    "name" : "Bb min",
    "waveformKey" : "Tru-Arpy-Bb-min-Bb--.wav",
    "transientSeconds" : 0.0,
    "lengthSeconds" : 8.227,
    "loopBeats" : 8.0,
    "tempo" : 120.0,
    "intensity" : 0.5,
    "event" : "PAD",
    "volume" : 1.0,
    "tones" : "Bb -"
  }, {
    "id" : "512504ca-6ea7-48fb-8080-e304f569b9ed",
    "instrumentId" : "f0c9f024-4f4c-11ed-b752-8bfe000d6dd5",
    "name" : "B min",
    "waveformKey" : "Tru-Arpy-B-min-B--.wav",
    "transientSeconds" : 0.0,
    "lengthSeconds" : 8.227,
    "loopBeats" : 8.0,
    "tempo" : 120.0,
    "intensity" : 0.5,
    "event" : "PAD",
    "volume" : 1.0,
    "tones" : "B -"
  }, {
    "id" : "15cee510-aa77-470c-b0fa-555d6984a730",
    "instrumentId" : "f0c9f024-4f4c-11ed-b752-8bfe000d6dd5",
    "name" : "Gb maj7add9",
    "waveformKey" : "Tru-Arpy-Gb-maj7add9-Gb-maj7add9.wav",
    "transientSeconds" : 0.0,
    "lengthSeconds" : 8.227,
    "loopBeats" : 8.0,
    "tempo" : 120.0,
    "intensity" : 0.5,
    "event" : "PAD",
    "volume" : 1.0,
    "tones" : "Gb maj7add9"
  }, {
    "id" : "5be1e245-d75b-4cf9-a8f9-f4c9e7f26a72",
    "instrumentId" : "f0c9f024-4f4c-11ed-b752-8bfe000d6dd5",
    "name" : "C dim",
    "waveformKey" : "Tru-Arpy-C-dim-C-dim.wav",
    "transientSeconds" : 0.0,
    "lengthSeconds" : 8.227,
    "loopBeats" : 8.0,
    "tempo" : 120.0,
    "intensity" : 0.5,
    "event" : "PAD",
    "volume" : 1.0,
    "tones" : "C dim"
  }, {
    "id" : "78443787-a967-4642-8b2c-3916519a7ff1",
    "instrumentId" : "f0c9f024-4f4c-11ed-b752-8bfe000d6dd5",
    "name" : "D 7b9",
    "waveformKey" : "Tru-Arpy-D-7b9-D-7b9.wav",
    "transientSeconds" : 0.0,
    "lengthSeconds" : 8.227,
    "loopBeats" : 8.0,
    "tempo" : 120.0,
    "intensity" : 0.5,
    "event" : "PAD",
    "volume" : 1.0,
    "tones" : "D 7b9"
  }, {
    "id" : "7e7daeb3-7f68-47ac-9470-8d19efa83c7c",
    "instrumentId" : "f0c9f024-4f4c-11ed-b752-8bfe000d6dd5",
    "name" : "B sus4",
    "waveformKey" : "Tru-Arpy-B-sus4-B-sus4.wav",
    "transientSeconds" : 0.0,
    "lengthSeconds" : 8.227,
    "loopBeats" : 8.0,
    "tempo" : 120.0,
    "intensity" : 0.5,
    "event" : "PAD",
    "volume" : 1.0,
    "tones" : "B sus4"
  }, {
    "id" : "2473c2e3-25c6-4c9c-967a-70b4a92d8c90",
    "instrumentId" : "f0c9f024-4f4c-11ed-b752-8bfe000d6dd5",
    "name" : "C -7b5",
    "waveformKey" : "Tru-Arpy-C--7b5-C--7b5.wav",
    "transientSeconds" : 0.0,
    "lengthSeconds" : 8.227,
    "loopBeats" : 8.0,
    "tempo" : 120.0,
    "intensity" : 0.5,
    "event" : "PAD",
    "volume" : 1.0,
    "tones" : "C -7b5"
  }, {
    "id" : "74878d63-e82c-46a3-ab3e-0e0c48713f94",
    "instrumentId" : "f0c9f024-4f4c-11ed-b752-8bfe000d6dd5",
    "name" : "C dim7",
    "waveformKey" : "Tru-Arpy-C-dim7-C-dim7.wav",
    "transientSeconds" : 0.0,
    "lengthSeconds" : 8.227,
    "loopBeats" : 8.0,
    "tempo" : 120.0,
    "intensity" : 0.5,
    "event" : "PAD",
    "volume" : 1.0,
    "tones" : "C dim7"
  }, {
    "id" : "d725eefc-c6b0-43c3-a2dc-1bae1616fe73",
    "instrumentId" : "f0c9f024-4f4c-11ed-b752-8bfe000d6dd5",
    "name" : "Gb -7",
    "waveformKey" : "Tru-Arpy-Gb--7-Gb--7.wav",
    "transientSeconds" : 0.0,
    "lengthSeconds" : 8.227,
    "loopBeats" : 8.0,
    "tempo" : 120.0,
    "intensity" : 0.5,
    "event" : "PAD",
    "volume" : 1.0,
    "tones" : "Gb -7"
  }, {
    "id" : "129b5884-6161-4ace-ac18-6aa1ae7ddacb",
    "instrumentId" : "f0c9f024-4f4c-11ed-b752-8bfe000d6dd5",
    "name" : "F min",
    "waveformKey" : "Tru-Arpy-F-min-F--.wav",
    "transientSeconds" : 0.0,
    "lengthSeconds" : 8.227,
    "loopBeats" : 8.0,
    "tempo" : 120.0,
    "intensity" : 0.5,
    "event" : "PAD",
    "volume" : 1.0,
    "tones" : "F -"
  }, {
    "id" : "c6f69a19-36c2-495d-a6e8-1d401812050b",
    "instrumentId" : "f0c9f024-4f4c-11ed-b752-8bfe000d6dd5",
    "name" : "Db 7",
    "waveformKey" : "Tru-Arpy-Db-7-Db-7.wav",
    "transientSeconds" : 0.0,
    "lengthSeconds" : 8.227,
    "loopBeats" : 8.0,
    "tempo" : 120.0,
    "intensity" : 0.5,
    "event" : "PAD",
    "volume" : 1.0,
    "tones" : "Db 7"
  }, {
    "id" : "d7572bdc-2d2b-47d8-a75a-6c9901396b43",
    "instrumentId" : "f0c9f024-4f4c-11ed-b752-8bfe000d6dd5",
    "name" : "B -7add9",
    "waveformKey" : "Tru-Arpy-B--7add9-B--7add9.wav",
    "transientSeconds" : 0.0,
    "lengthSeconds" : 8.227,
    "loopBeats" : 8.0,
    "tempo" : 120.0,
    "intensity" : 0.5,
    "event" : "PAD",
    "volume" : 1.0,
    "tones" : "B -7add9"
  }, {
    "id" : "c80cba0a-3926-4f98-b500-d1bd15acee6b",
    "instrumentId" : "f0c9f024-4f4c-11ed-b752-8bfe000d6dd5",
    "name" : "G aug7",
    "waveformKey" : "Tru-Arpy-G-aug7-G-aug7.wav",
    "transientSeconds" : 0.0,
    "lengthSeconds" : 8.227,
    "loopBeats" : 8.0,
    "tempo" : 120.0,
    "intensity" : 0.5,
    "event" : "PAD",
    "volume" : 1.0,
    "tones" : "G aug7"
  }, {
    "id" : "9a756202-14f6-49ef-a44b-6deceb9bf890",
    "instrumentId" : "f0c9f024-4f4c-11ed-b752-8bfe000d6dd5",
    "name" : "B -7",
    "waveformKey" : "Tru-Arpy-B--7-B--7.wav",
    "transientSeconds" : 0.0,
    "lengthSeconds" : 8.227,
    "loopBeats" : 8.0,
    "tempo" : 120.0,
    "intensity" : 0.5,
    "event" : "PAD",
    "volume" : 1.0,
    "tones" : "B -7"
  }, {
    "id" : "ba91565d-27b4-4d20-9e34-ac43e85614bc",
    "instrumentId" : "f0c9f024-4f4c-11ed-b752-8bfe000d6dd5",
    "name" : "Db 7sus4",
    "waveformKey" : "Tru-Arpy-Db-7sus4-Db-7sus4.wav",
    "transientSeconds" : 0.0,
    "lengthSeconds" : 8.227,
    "loopBeats" : 8.0,
    "tempo" : 120.0,
    "intensity" : 0.5,
    "event" : "PAD",
    "volume" : 1.0,
    "tones" : "Db 7sus4"
  }, {
    "id" : "80979b68-ebd2-4098-adae-e2cb435ce64a",
    "instrumentId" : "f0c9f024-4f4c-11ed-b752-8bfe000d6dd5",
    "name" : "Ab -7",
    "waveformKey" : "Tru-Arpy-Ab--7-Ab--7.wav",
    "transientSeconds" : 0.0,
    "lengthSeconds" : 8.227,
    "loopBeats" : 8.0,
    "tempo" : 120.0,
    "intensity" : 0.5,
    "event" : "PAD",
    "volume" : 1.0,
    "tones" : "Ab -7"
  }, {
    "id" : "6f959775-8c0b-4727-a9b5-e4eb00ca419e",
    "instrumentId" : "f0c9f024-4f4c-11ed-b752-8bfe000d6dd5",
    "name" : "D sus4",
    "waveformKey" : "Tru-Arpy-D-sus4-D-sus4.wav",
    "transientSeconds" : 0.0,
    "lengthSeconds" : 8.227,
    "loopBeats" : 8.0,
    "tempo" : 120.0,
    "intensity" : 0.5,
    "event" : "PAD",
    "volume" : 1.0,
    "tones" : "D sus4"
  }, {
    "id" : "a682f2b3-0a7c-40ec-83d8-675d8fc8662a",
    "instrumentId" : "f0c9f024-4f4c-11ed-b752-8bfe000d6dd5",
    "name" : "F dim7",
    "waveformKey" : "Tru-Arpy-F-dim7-F-dim7.wav",
    "transientSeconds" : 0.0,
    "lengthSeconds" : 8.227,
    "loopBeats" : 8.0,
    "tempo" : 120.0,
    "intensity" : 0.5,
    "event" : "PAD",
    "volume" : 1.0,
    "tones" : "F dim7"
  }, {
    "id" : "ab92af7e-9abe-4370-b23d-fa79cd67d5ca",
    "instrumentId" : "f0c9f024-4f4c-11ed-b752-8bfe000d6dd5",
    "name" : "Ab min",
    "waveformKey" : "Tru-Arpy-Ab-min-Ab--.wav",
    "transientSeconds" : 0.0,
    "lengthSeconds" : 8.227,
    "loopBeats" : 8.0,
    "tempo" : 120.0,
    "intensity" : 0.5,
    "event" : "PAD",
    "volume" : 1.0,
    "tones" : "Ab -"
  }, {
    "id" : "33872566-f632-4fdb-b955-f6a2a938d70c",
    "instrumentId" : "f0c9f024-4f4c-11ed-b752-8bfe000d6dd5",
    "name" : "C maj7add9",
    "waveformKey" : "Tru-Arpy-C-maj7add9-C-maj7add9.wav",
    "transientSeconds" : 0.0,
    "lengthSeconds" : 8.227,
    "loopBeats" : 8.0,
    "tempo" : 120.0,
    "intensity" : 0.5,
    "event" : "PAD",
    "volume" : 1.0,
    "tones" : "C maj7add9"
  }, {
    "id" : "3364569f-ff23-44d5-99f3-049d998f6820",
    "instrumentId" : "f0c9f024-4f4c-11ed-b752-8bfe000d6dd5",
    "name" : "Ab -7add9",
    "waveformKey" : "Tru-Arpy-Ab--7add9-Ab--7add9.wav",
    "transientSeconds" : 0.0,
    "lengthSeconds" : 8.227,
    "loopBeats" : 8.0,
    "tempo" : 120.0,
    "intensity" : 0.5,
    "event" : "PAD",
    "volume" : 1.0,
    "tones" : "Ab -7add9"
  }, {
    "id" : "c445fe27-7701-419d-b324-e69b0f8d4c01",
    "instrumentId" : "f0c9f024-4f4c-11ed-b752-8bfe000d6dd5",
    "name" : "E sus2",
    "waveformKey" : "Tru-Arpy-E-sus2-E-sus2.wav",
    "transientSeconds" : 0.0,
    "lengthSeconds" : 8.227,
    "loopBeats" : 8.0,
    "tempo" : 120.0,
    "intensity" : 0.5,
    "event" : "PAD",
    "volume" : 1.0,
    "tones" : "E sus2"
  }, {
    "id" : "233d69cf-3aa9-4387-be7e-1fe109d29b5f",
    "instrumentId" : "f0c9f024-4f4c-11ed-b752-8bfe000d6dd5",
    "name" : "A -7b5",
    "waveformKey" : "Tru-Arpy-A--7b5-A--7b5.wav",
    "transientSeconds" : 0.0,
    "lengthSeconds" : 8.227,
    "loopBeats" : 8.0,
    "tempo" : 120.0,
    "intensity" : 0.5,
    "event" : "PAD",
    "volume" : 1.0,
    "tones" : "A -7b5"
  }, {
    "id" : "620e0ec1-9d80-4f2c-9264-20d2df572a4d",
    "instrumentId" : "f0c9f024-4f4c-11ed-b752-8bfe000d6dd5",
    "name" : "Eb min",
    "waveformKey" : "Tru-Arpy-Eb-min-Eb--.wav",
    "transientSeconds" : 0.0,
    "lengthSeconds" : 8.227,
    "loopBeats" : 8.0,
    "tempo" : 120.0,
    "intensity" : 0.5,
    "event" : "PAD",
    "volume" : 1.0,
    "tones" : "Eb -"
  }, {
    "id" : "2e8d2204-13b7-45ca-982c-4f0f6cd981db",
    "instrumentId" : "f0c9f024-4f4c-11ed-b752-8bfe000d6dd5",
    "name" : "D aug",
    "waveformKey" : "Tru-Arpy-D-aug-D-aug.wav",
    "transientSeconds" : 0.0,
    "lengthSeconds" : 8.227,
    "loopBeats" : 8.0,
    "tempo" : 120.0,
    "intensity" : 0.5,
    "event" : "PAD",
    "volume" : 1.0,
    "tones" : "D aug"
  }, {
    "id" : "bdf57837-3e6e-4167-8676-e0bb1a8fe45c",
    "instrumentId" : "f0c9f024-4f4c-11ed-b752-8bfe000d6dd5",
    "name" : "Bb 7sus4",
    "waveformKey" : "Tru-Arpy-Bb-7sus4-Bb-7sus4.wav",
    "transientSeconds" : 0.0,
    "lengthSeconds" : 8.227,
    "loopBeats" : 8.0,
    "tempo" : 120.0,
    "intensity" : 0.5,
    "event" : "PAD",
    "volume" : 1.0,
    "tones" : "Bb 7sus4"
  }, {
    "id" : "5d9bef6b-d426-44eb-851c-2b85fe67fa14",
    "instrumentId" : "f0c9f024-4f4c-11ed-b752-8bfe000d6dd5",
    "name" : "E sus4",
    "waveformKey" : "Tru-Arpy-E-sus4-E-sus4.wav",
    "transientSeconds" : 0.0,
    "lengthSeconds" : 8.227,
    "loopBeats" : 8.0,
    "tempo" : 120.0,
    "intensity" : 0.5,
    "event" : "PAD",
    "volume" : 1.0,
    "tones" : "E sus4"
  }, {
    "id" : "d889c8ea-5a46-4139-8c48-6eeea61aba42",
    "instrumentId" : "f0c9f024-4f4c-11ed-b752-8bfe000d6dd5",
    "name" : "Ab",
    "waveformKey" : "Tru-Arpy-Ab-Ab.wav",
    "transientSeconds" : 0.0,
    "lengthSeconds" : 8.227,
    "loopBeats" : 8.0,
    "tempo" : 120.0,
    "intensity" : 0.5,
    "event" : "PAD",
    "volume" : 1.0,
    "tones" : "Ab"
  }, {
    "id" : "9909a525-40ad-43b1-a50b-53bc7e7a0f1e",
    "instrumentId" : "f0c9f024-4f4c-11ed-b752-8bfe000d6dd5",
    "name" : "Eb sus2",
    "waveformKey" : "Tru-Arpy-Eb-sus2-Eb-sus2.wav",
    "transientSeconds" : 0.0,
    "lengthSeconds" : 8.227,
    "loopBeats" : 8.0,
    "tempo" : 120.0,
    "intensity" : 0.5,
    "event" : "PAD",
    "volume" : 1.0,
    "tones" : "Eb sus2"
  }, {
    "id" : "80db28fe-f9d1-4794-97ec-310a2eea378f",
    "instrumentId" : "f0c9f024-4f4c-11ed-b752-8bfe000d6dd5",
    "name" : "Bb -7",
    "waveformKey" : "Tru-Arpy-Bb--7-Bb--7.wav",
    "transientSeconds" : 0.0,
    "lengthSeconds" : 8.227,
    "loopBeats" : 8.0,
    "tempo" : 120.0,
    "intensity" : 0.5,
    "event" : "PAD",
    "volume" : 1.0,
    "tones" : "Bb -7"
  }, {
    "id" : "b145e61f-b86f-4425-ad90-0782c33205d3",
    "instrumentId" : "f0c9f024-4f4c-11ed-b752-8bfe000d6dd5",
    "name" : "C 7",
    "waveformKey" : "Tru-Arpy-C-7-C-7.wav",
    "transientSeconds" : 0.0,
    "lengthSeconds" : 8.227,
    "loopBeats" : 8.0,
    "tempo" : 120.0,
    "intensity" : 0.5,
    "event" : "PAD",
    "volume" : 1.0,
    "tones" : "C 7"
  }, {
    "id" : "de14f318-2033-446d-a639-68932443015f",
    "instrumentId" : "f0c9f024-4f4c-11ed-b752-8bfe000d6dd5",
    "name" : "Db -7",
    "waveformKey" : "Tru-Arpy-Db--7-Db--7.wav",
    "transientSeconds" : 0.0,
    "lengthSeconds" : 8.227,
    "loopBeats" : 8.0,
    "tempo" : 120.0,
    "intensity" : 0.5,
    "event" : "PAD",
    "volume" : 1.0,
    "tones" : "Db -7"
  }, {
    "id" : "191137a9-baa0-4149-a0b8-80c86de8a62f",
    "instrumentId" : "f0c9f024-4f4c-11ed-b752-8bfe000d6dd5",
    "name" : "Ab aug",
    "waveformKey" : "Tru-Arpy-Ab-aug-Ab-aug.wav",
    "transientSeconds" : 0.0,
    "lengthSeconds" : 8.227,
    "loopBeats" : 8.0,
    "tempo" : 120.0,
    "intensity" : 0.5,
    "event" : "PAD",
    "volume" : 1.0,
    "tones" : "Ab aug"
  }, {
    "id" : "aa773de2-3be2-4ff8-bbb6-4f22a7d37b2f",
    "instrumentId" : "f0c9f024-4f4c-11ed-b752-8bfe000d6dd5",
    "name" : "C -7add9",
    "waveformKey" : "Tru-Arpy-C--7add9-C--7add9.wav",
    "transientSeconds" : 0.0,
    "lengthSeconds" : 8.227,
    "loopBeats" : 8.0,
    "tempo" : 120.0,
    "intensity" : 0.5,
    "event" : "PAD",
    "volume" : 1.0,
    "tones" : "C -7add9"
  }, {
    "id" : "1bd8fc48-c5fc-4603-9c16-df4512a50971",
    "instrumentId" : "f0c9f024-4f4c-11ed-b752-8bfe000d6dd5",
    "name" : "Db aug",
    "waveformKey" : "Tru-Arpy-Db-aug-Db-aug.wav",
    "transientSeconds" : 0.0,
    "lengthSeconds" : 8.226979,
    "loopBeats" : 8.0,
    "tempo" : 120.0,
    "intensity" : 0.5,
    "event" : "PAD",
    "volume" : 1.0,
    "tones" : "Db aug"
  }, {
    "id" : "36df3631-c3f5-4fac-9151-24324c9c3aa1",
    "instrumentId" : "f0c9f024-4f4c-11ed-b752-8bfe000d6dd5",
    "name" : "A maj7add9",
    "waveformKey" : "Tru-Arpy-A-maj7add9-A-maj7add9.wav",
    "transientSeconds" : 0.0,
    "lengthSeconds" : 8.227,
    "loopBeats" : 8.0,
    "tempo" : 120.0,
    "intensity" : 0.5,
    "event" : "PAD",
    "volume" : 1.0,
    "tones" : "A maj7add9"
  }, {
    "id" : "2c0a85da-b6c5-4473-a658-fdee8241de7a",
    "instrumentId" : "f0c9f024-4f4c-11ed-b752-8bfe000d6dd5",
    "name" : "G 7sus4",
    "waveformKey" : "Tru-Arpy-G-7sus4-G-7sus4.wav",
    "transientSeconds" : 0.0,
    "lengthSeconds" : 8.227,
    "loopBeats" : 8.0,
    "tempo" : 120.0,
    "intensity" : 0.5,
    "event" : "PAD",
    "volume" : 1.0,
    "tones" : "G 7sus4"
  }, {
    "id" : "99b33bd4-1677-4ab9-adfd-8e98d728d10f",
    "instrumentId" : "f0c9f024-4f4c-11ed-b752-8bfe000d6dd5",
    "name" : "F aug",
    "waveformKey" : "Tru-Arpy-F-aug-F-aug.wav",
    "transientSeconds" : 0.0,
    "lengthSeconds" : 8.227,
    "loopBeats" : 8.0,
    "tempo" : 120.0,
    "intensity" : 0.5,
    "event" : "PAD",
    "volume" : 1.0,
    "tones" : "F aug"
  }, {
    "id" : "20652b96-f95d-4b6d-a562-fd34d668a310",
    "instrumentId" : "f0c9f024-4f4c-11ed-b752-8bfe000d6dd5",
    "name" : "G dim",
    "waveformKey" : "Tru-Arpy-G-dim-G-dim.wav",
    "transientSeconds" : 0.0,
    "lengthSeconds" : 8.227,
    "loopBeats" : 8.0,
    "tempo" : 120.0,
    "intensity" : 0.5,
    "event" : "PAD",
    "volume" : 1.0,
    "tones" : "G dim"
  }, {
    "id" : "808212a4-9639-4d8a-812b-517c9dfebbd1",
    "instrumentId" : "f0c9f024-4f4c-11ed-b752-8bfe000d6dd5",
    "name" : "Ab 7",
    "waveformKey" : "Tru-Arpy-Ab-7-Ab-7.wav",
    "transientSeconds" : 0.0,
    "lengthSeconds" : 8.227,
    "loopBeats" : 8.0,
    "tempo" : 120.0,
    "intensity" : 0.5,
    "event" : "PAD",
    "volume" : 1.0,
    "tones" : "Ab 7"
  }, {
    "id" : "19f900e4-3886-4280-b65b-5de6eb568d1e",
    "instrumentId" : "f0c9f024-4f4c-11ed-b752-8bfe000d6dd5",
    "name" : "Db dim",
    "waveformKey" : "Tru-Arpy-Db-dim-Db-dim.wav",
    "transientSeconds" : 0.0,
    "lengthSeconds" : 8.227,
    "loopBeats" : 8.0,
    "tempo" : 120.0,
    "intensity" : 0.5,
    "event" : "PAD",
    "volume" : 1.0,
    "tones" : "Db dim"
  }, {
    "id" : "784f678a-1fc9-4748-a3d2-5a1689925cfc",
    "instrumentId" : "f0c9f024-4f4c-11ed-b752-8bfe000d6dd5",
    "name" : "Ab sus2",
    "waveformKey" : "Tru-Arpy-Ab-sus2-Ab-sus2.wav",
    "transientSeconds" : 0.0,
    "lengthSeconds" : 8.227,
    "loopBeats" : 8.0,
    "tempo" : 120.0,
    "intensity" : 0.5,
    "event" : "PAD",
    "volume" : 1.0,
    "tones" : "Ab sus2"
  }, {
    "id" : "7e0e8f4c-3a91-460c-a550-fafb19b1352a",
    "instrumentId" : "f0c9f024-4f4c-11ed-b752-8bfe000d6dd5",
    "name" : "Bb dim7",
    "waveformKey" : "Tru-Arpy-Bb-dim7-Bb-dim7.wav",
    "transientSeconds" : 0.0,
    "lengthSeconds" : 8.227,
    "loopBeats" : 8.0,
    "tempo" : 120.0,
    "intensity" : 0.5,
    "event" : "PAD",
    "volume" : 1.0,
    "tones" : "Bb dim7"
  }, {
    "id" : "21f12c4c-a1d4-446f-992b-87df1169d06a",
    "instrumentId" : "f0c9f024-4f4c-11ed-b752-8bfe000d6dd5",
    "name" : "Eb 7b9",
    "waveformKey" : "Tru-Arpy-Eb-7b9-Eb-7b9.wav",
    "transientSeconds" : 0.0,
    "lengthSeconds" : 6.178999,
    "loopBeats" : 8.0,
    "tempo" : 120.0,
    "intensity" : 0.5,
    "event" : "PAD",
    "volume" : 1.0,
    "tones" : "Eb 7b9"
  }, {
    "id" : "01b796bb-6893-4e5a-9b0a-4c0eeea3d290",
    "instrumentId" : "f0c9f024-4f4c-11ed-b752-8bfe000d6dd5",
    "name" : "D -7",
    "waveformKey" : "Tru-Arpy-D--7-D--7.wav",
    "transientSeconds" : 0.0,
    "lengthSeconds" : 8.227,
    "loopBeats" : 8.0,
    "tempo" : 120.0,
    "intensity" : 0.5,
    "event" : "PAD",
    "volume" : 1.0,
    "tones" : "D -7"
  }, {
    "id" : "d3412c1f-c127-480d-ac0f-14854577d07b",
    "instrumentId" : "f0c9f024-4f4c-11ed-b752-8bfe000d6dd5",
    "name" : "Db -7add9",
    "waveformKey" : "Tru-Arpy-Db--7add9-Db--7add9.wav",
    "transientSeconds" : 0.0,
    "lengthSeconds" : 8.227,
    "loopBeats" : 8.0,
    "tempo" : 120.0,
    "intensity" : 0.5,
    "event" : "PAD",
    "volume" : 1.0,
    "tones" : "Db -7add9"
  }, {
    "id" : "50c8392c-b52c-4f09-80df-c14034c98564",
    "instrumentId" : "f0c9f024-4f4c-11ed-b752-8bfe000d6dd5",
    "name" : "C sus4",
    "waveformKey" : "Tru-Arpy-C-sus4-C-sus4.wav",
    "transientSeconds" : 0.0,
    "lengthSeconds" : 8.227,
    "loopBeats" : 8.0,
    "tempo" : 120.0,
    "intensity" : 0.5,
    "event" : "PAD",
    "volume" : 1.0,
    "tones" : "C sus4"
  }, {
    "id" : "df392e01-8fb9-4ae9-919f-1e6d6a5a2134",
    "instrumentId" : "f0c9f024-4f4c-11ed-b752-8bfe000d6dd5",
    "name" : "B 7b9",
    "waveformKey" : "Tru-Arpy-B-7b9-B-7b9.wav",
    "transientSeconds" : 0.0,
    "lengthSeconds" : 8.227,
    "loopBeats" : 8.0,
    "tempo" : 120.0,
    "intensity" : 0.5,
    "event" : "PAD",
    "volume" : 1.0,
    "tones" : "B 7b9"
  }, {
    "id" : "faec9eea-e601-404a-9e6b-5a4fb24e27d3",
    "instrumentId" : "f0c9f024-4f4c-11ed-b752-8bfe000d6dd5",
    "name" : "Eb maj7add9",
    "waveformKey" : "Tru-Arpy-Eb-maj7add9-Eb-maj7add9.wav",
    "transientSeconds" : 0.0,
    "lengthSeconds" : 8.227,
    "loopBeats" : 8.0,
    "tempo" : 120.0,
    "intensity" : 0.5,
    "event" : "PAD",
    "volume" : 1.0,
    "tones" : "Eb maj7add9"
  }, {
    "id" : "25c316cf-2ace-42c5-90e9-ddc84083b050",
    "instrumentId" : "f0c9f024-4f4c-11ed-b752-8bfe000d6dd5",
    "name" : "Gb -7add9",
    "waveformKey" : "Tru-Arpy-Gb--7add9-Gb--7add9.wav",
    "transientSeconds" : 0.0,
    "lengthSeconds" : 8.227,
    "loopBeats" : 8.0,
    "tempo" : 120.0,
    "intensity" : 0.5,
    "event" : "PAD",
    "volume" : 1.0,
    "tones" : "Gb -7add9"
  }, {
    "id" : "c3005eb0-9e52-4331-932a-f80564489441",
    "instrumentId" : "f0c9f024-4f4c-11ed-b752-8bfe000d6dd5",
    "name" : "D aug7",
    "waveformKey" : "Tru-Arpy-D-aug7-D-aug7.wav",
    "transientSeconds" : 0.0,
    "lengthSeconds" : 8.227,
    "loopBeats" : 8.0,
    "tempo" : 120.0,
    "intensity" : 0.5,
    "event" : "PAD",
    "volume" : 1.0,
    "tones" : "D aug7"
  }, {
    "id" : "eab94c1b-7b8b-4bdf-bacf-4813392aacf6",
    "instrumentId" : "f0c9f024-4f4c-11ed-b752-8bfe000d6dd5",
    "name" : "G aug",
    "waveformKey" : "Tru-Arpy-G-aug-G-aug.wav",
    "transientSeconds" : 0.0,
    "lengthSeconds" : 8.227,
    "loopBeats" : 8.0,
    "tempo" : 120.0,
    "intensity" : 0.5,
    "event" : "PAD",
    "volume" : 1.0,
    "tones" : "G aug"
  }, {
    "id" : "628a0a44-3eb4-4130-b9ef-d39a1755b29d",
    "instrumentId" : "f0c9f024-4f4c-11ed-b752-8bfe000d6dd5",
    "name" : "F sus2",
    "waveformKey" : "Tru-Arpy-F-sus2-F-sus2.wav",
    "transientSeconds" : 0.0,
    "lengthSeconds" : 8.227,
    "loopBeats" : 8.0,
    "tempo" : 120.0,
    "intensity" : 0.5,
    "event" : "PAD",
    "volume" : 1.0,
    "tones" : "F sus2"
  }, {
    "id" : "e7f3f941-8f0f-4703-a02d-d1137d18e66f",
    "instrumentId" : "f0c9f024-4f4c-11ed-b752-8bfe000d6dd5",
    "name" : "E",
    "waveformKey" : "Tru-Arpy-E-E.wav",
    "transientSeconds" : 0.0,
    "lengthSeconds" : 8.227,
    "loopBeats" : 8.0,
    "tempo" : 120.0,
    "intensity" : 0.5,
    "event" : "PAD",
    "volume" : 1.0,
    "tones" : "E"
  }, {
    "id" : "9d6d3377-cd14-47a3-b820-9f3832969ad4",
    "instrumentId" : "f0c9f024-4f4c-11ed-b752-8bfe000d6dd5",
    "name" : "D sus2",
    "waveformKey" : "Tru-Arpy-D-sus2-D-sus2.wav",
    "transientSeconds" : 0.0,
    "lengthSeconds" : 8.227,
    "loopBeats" : 8.0,
    "tempo" : 120.0,
    "intensity" : 0.5,
    "event" : "PAD",
    "volume" : 1.0,
    "tones" : "D sus2"
  }, {
    "id" : "e0fc0067-0919-437f-a3a6-152e7230f1b2",
    "instrumentId" : "f0c9f024-4f4c-11ed-b752-8bfe000d6dd5",
    "name" : "G 7b9",
    "waveformKey" : "Tru-Arpy-G-7b9-G-7b9.wav",
    "transientSeconds" : 0.0,
    "lengthSeconds" : 10.274999,
    "loopBeats" : 8.0,
    "tempo" : 120.0,
    "intensity" : 0.5,
    "event" : "PAD",
    "volume" : 1.0,
    "tones" : "G 7b9"
  }, {
    "id" : "907e454b-9b35-440c-be00-1fa3249acfcd",
    "instrumentId" : "f0c9f024-4f4c-11ed-b752-8bfe000d6dd5",
    "name" : "B 7sus4",
    "waveformKey" : "Tru-Arpy-B-7sus4-B-7sus4.wav",
    "transientSeconds" : 0.0,
    "lengthSeconds" : 8.227,
    "loopBeats" : 8.0,
    "tempo" : 120.0,
    "intensity" : 0.5,
    "event" : "PAD",
    "volume" : 1.0,
    "tones" : "B 7sus4"
  }, {
    "id" : "b908f0f2-caf0-4341-802b-6c5d864fc088",
    "instrumentId" : "f0c9f024-4f4c-11ed-b752-8bfe000d6dd5",
    "name" : "E min",
    "waveformKey" : "Tru-Arpy-E-min-E--.wav",
    "transientSeconds" : 0.0,
    "lengthSeconds" : 8.227,
    "loopBeats" : 8.0,
    "tempo" : 120.0,
    "intensity" : 0.5,
    "event" : "PAD",
    "volume" : 1.0,
    "tones" : "E -"
  }, {
    "id" : "409bab2e-3a1e-4b9b-923f-7105af898c78",
    "instrumentId" : "f0c9f024-4f4c-11ed-b752-8bfe000d6dd5",
    "name" : "Ab aug7",
    "waveformKey" : "Tru-Arpy-Ab-aug7-Ab-aug7.wav",
    "transientSeconds" : 0.0,
    "lengthSeconds" : 8.227,
    "loopBeats" : 8.0,
    "tempo" : 120.0,
    "intensity" : 0.5,
    "event" : "PAD",
    "volume" : 1.0,
    "tones" : "Ab aug7"
  }, {
    "id" : "dc265be7-54d7-4c1b-8f70-163d821bf0a7",
    "instrumentId" : "f0c9f024-4f4c-11ed-b752-8bfe000d6dd5",
    "name" : "B dim",
    "waveformKey" : "Tru-Arpy-B-dim-B-dim.wav",
    "transientSeconds" : 0.0,
    "lengthSeconds" : 8.227,
    "loopBeats" : 8.0,
    "tempo" : 120.0,
    "intensity" : 0.5,
    "event" : "PAD",
    "volume" : 1.0,
    "tones" : "B dim"
  }, {
    "id" : "b459ba12-a39c-4b94-aea7-3055b9763238",
    "instrumentId" : "f0c9f024-4f4c-11ed-b752-8bfe000d6dd5",
    "name" : "C aug",
    "waveformKey" : "Tru-Arpy-C-aug-C-aug.wav",
    "transientSeconds" : 0.0,
    "lengthSeconds" : 8.226979,
    "loopBeats" : 8.0,
    "tempo" : 120.0,
    "intensity" : 0.5,
    "event" : "PAD",
    "volume" : 1.0,
    "tones" : "C aug"
  } ],
  "instruments" : [ {
    "id" : "f0c9f024-4f4c-11ed-b752-8bfe000d6dd5",
    "libraryId" : "c9745e10-e6bf-11ec-ae61-0f19490a8744",
    "type" : "Pad",
    "state" : "Published",
    "name" : "Tru Arpy",
    "config" : "isAudioSelectionPersistent = true\nisMultiphonic = false\nisOneShot = true\nisOneShotCutoffEnabled = false\nisTonal = false\noneShotObserveLengthOfEvents = []\nreleaseMillis = 5\n",
    "isDeleted" : false,
    "volume" : 1.0,
    "mode" : "Chord",
    "updatedAt" : 1710457155883
  } ],
  "instrumentMemes" : [ {
    "id" : "75092ac0-4f4e-11ed-982d-2b66cd98e125",
    "instrumentId" : "f0c9f024-4f4c-11ed-b752-8bfe000d6dd5",
    "name" : "NAGOYA"
  } ]
}